Workbook
Name OutcomesList: '[1]Lookups Tables'!$J$3:$J$12
Name Percentage: '[1]Lookups Tables'!$L$4:$L$23

Sheet Main
A1: Course Name: | F1: Semester:
A2: Course Code: | F2: Instructor:
A4: SO | F4: Mapped PIs | J4: Mapped CLO
A5: SO4 | B5: =VLOOKUP(A5,'Lookup Tables'!$L$1:$M$7,2,FALSE) -> An ability to recognize ethical and professional responsibilities in engineering situations and make informed judgments, which must consider the impact of engineering solutions in global, economic, environmental, and societal contexts. | F5: PI41. Recognize ethical and professional responsibilities in engineering situations PI42 Make informed judgments considering the impact of engineering solutions in global, societal, economic, and environmental contexts | J5: Add the CLO mapaped to this SO
A6: SO4 | B6: =VLOOKUP(A6,'Lookup Tables'!$L$1:$M$7,2,FALSE) -> An ability to recognize ethical and professional responsibilities in engineering situations and make informed judgments, which must consider the impact of engineering solutions in global, economic, environmental, and societal contexts. | F6: PI41 Recognize ethical and professional responsibilities in engineering situations PI42 Make informed judgments considering the impact of engineering solutions in global, societal, economic, and environmental contexts | J6: 3.1 Recognize the engineering profession and the importance of ethical and legal factors in professional duties
A8: Please provide the information below to support the preparation of the Student Outcome assessment report.
A9: Assessment Method and Evidence Source | C9: Relevant SO4 Considerations | F9: Explain how the assessment addresses each PI
A10: List all SO4 assessment instruments and indicate whether each provides team-based or individual evidence. Each instrument should be supported by corresponding evidence when collected, except structured oral assessment. Team based: -final design report, -presentation -prototype demonstration individaul assssment: -individual oral defense, -oral presentation discussion, -assignment, - exam (mention the exam and question number, e.g. Final exam, Q4. ] | C10: [List all relevant contexts (considerations) that will be considered in the assessment. Choose from the list below ]. -global, -societal, -economic, -environmental | F10: [Add brief description for how the assessment addressed each PI. See the example below. Below is an example for radar system project] PI 41: The assessment requires students to identify and address relevant ethical and professional responsibilities associated with the radar system design. Students must consider how engineering decisions related to system operation, safety, reliability, privacy, or potential misuse may affect users or other stakeholders, and explain how these responsibilities influence an engineering decision or recommendation. PI 42: The assessment requires students to consider the relevant global, societal, economic, and/or environmental impacts of the radar system and use these considerations to make an informed engineering judgment or decision. Students must identify applicable impacts, analyze their significance to the proposed solution, and explain how they influence a design decision, recommendation, or conclusion.

Sheet  Rubric
A1: Assessment Rubric
A2: Assessment item | B2: Above Expectation (3) | C2: Meet Expectation (2) | D2: Developing Expectation (1) | E2: Below Expectation (0) | F2: Checklist for Assessment (Project) | G2: Checklist for Assessment (Exam)
A4: PI41 – Recognize ethical and professional responsibilities in engineering situations | B4: Clearly identifies and explains relevant ethical and professional responsibilities and their implications in the engineering situation. | C4: Identifies and explains relevant ethical and professional responsibilities in the engineering situation. | D4: Identifies an ethical or professional responsibility, but the explanation or connection to the engineering situation is limited. | E4: Fails to identify relevant ethical or professional responsibilities or misinterprets them. | F4: Team assessment (Report): • Are relevant ethical and professional responsibilities identified? • Are they connected to the engineering situation or decision? Individual Assessment: • Identify one ethical or professional responsibility and explain how it relates to an engineering decision. | G4: • Does the student identify the relevant ethical and/or professional responsibility in the engineering situation? • Does the student explain how it relates to an engineering decision, action, or consequence?
A5: PI42 – Make informed judgments considering the impact of engineering solutions in global, societal, economic, and environmental contexts | B5: Makes a clear, well-justified informed judgment by analyzing relevant impacts in applicable global, societal, economic, and/or environmental contexts. | C5: Makes an appropriate informed judgment by considering and explaining the main relevant impacts in applicable contexts. | D5: Makes a limited judgment; some relevant impacts are identified, but analysis or justification is incomplete. | E5: Does not make a meaningful informed judgment; relevant impacts are missing, incorrect, or not connected to the judgment. | F5: Team assessment (Report): • Are the applicable global, societal, economic, and/or environmental impacts identified and considered? • Does the analysis support a clear engineering judgment or decision? Individual assessment: • Identify one relevant impact and explain how it influenced an engineering judgment or decision. | G5: • Does the student identify and consider one or more relevant global, societal, economic, and/or environmental impacts? • Does the student use these impacts to justify an engineering judgment or decision?
A6: Assessment Note: • Team-based assessment is based on team evidence (e.g., final report). • Individual attainment may be verified through structured oral questions or individual exam questions. • Use the checklist column(s) applicable to the selected assessment method; non-applicable checklist items may be left unused. • For project-based assessment with oral individual verification, use the project checklist. For project-based assessment with individual exam verification, use both the project and exam checklists. For exam-only assessment, use the exam checklist.

Sheet SO4 Rubric
A1: SO4 Rubric
A2: Assessment item | B2: Above | C2: Meet | D2: Developing | E2: Below | F2: Checklist for Assessment | G2: ="ID# " &#REF! -> #REF! | I2: ="ID# " &#REF! -> #REF! | K2: ="ID# " &#REF! -> #REF! | M2: ="ID# " &#REF! -> #REF! | O2: ="ID# " &#REF! -> #REF! | Q2: ="ID# " &#REF! -> #REF! | S2: ="ID# " &#REF! -> #REF! | U2: ="ID# " &#REF! -> #REF! | W2: ="ID# " &#REF! -> #REF! | Y2: ="ID# " &#REF! -> #REF! | AA2: ="ID# " &#REF! -> #REF! | AC2: ="ID# " &#REF! -> #REF! | AE2: ="ID# " &#REF! -> #REF! | AG2: ="ID# " &#REF! -> #REF!
B3: Expectation (3) | C3: Expectation (2) | D3: Expectation (1) | E3: Expectation (0) | G3: Comment | H3: score (0-3) | I3: Comment | J3: score (0-3) | K3: Comment | L3: score (0-3) | M3: Comment | N3: score (0-3) | O3: Comment | P3: score (0-3) | Q3: Comment | R3: score (0-3) | S3: Comment | T3: score (0-3) | U3: Comment | V3: score (0-3) | W3: Comment | X3: score (0-3) | Y3: Comment | Z3: score (0-3) | AA3: Comment | AB3: score (0-3) | AC3: Comment | AD3: score (0-3) | AE3: Comment | AF3: score (0-3) | AG3: Comment | AH3: score (0-3)
A4: PI41. Recognize ethical and professional responsibilities in engineering situations | B4: Identifies the ethical responsibilities and references at least one applicable professional code or standard (e.g., IEEE, NSPE, ISO). | C4: Describes relevant ethical responsibilities and refers generally to professional obligations or standards (without a specific citation). | D4: Acknowledges that an ethical issue exists but provides vague or incomplete responsibilities and no clear connection to professional standards. | E4: Fails to identify the ethical issue or misinterprets it. | F4: • Does the student clearly identify the ethical issue(s) in the scenario? | G4: Clearly identifies safety responsibilities: emergency stops, fail-safe procedures. Addresses misuse and cybersecurity: limiting physical access, considering unauthorized access. Explicitly refers to professional codes/standards: IEEE and NSPE. Mentions transparency and honesty: explaining decisions, assessments, and system limitations. Connects ethics back to the technical solution: how the drive-by-wire method maintains safety. | H4: 3 | I4: Explicitly addresses safety responsibilities: emergency stops, fail-safe procedures. Considers misuse and cybersecurity: restricted physical access, concern about unauthorized access to control systems. Refers directly to professional codes and standards (IEEE, NSPE) and links them to: transparency in conclusions and assessments, being open about limitations, integrating safety in the drive-by-wire method. | J4: 3 | K4: Explicitly cites IEEE and NSPE codes and standards and links them to behavior: academic integrity, professionalism. Emphasizes truth and transparency in findings and evaluations. Acknowledges need to be honest about limits and how safety is incorporated. Describes fail-safe procedures, emergency stop, and cybersecurity issues (unauthorized access) with restricted physical access to reduce misuse. | L4: 3 | M4: Clearly frames DBW as safety-critical, noting failures, unintended behavior, and liability as major ethical concerns. Explicitly cites IEEE and NSPE standards and connects them to integrity in testing and reporting. Puts safety above performance (emergency stop circuits, safe-state defaults, robust signal handling). Acknowledges hacking / misuse risks and mitigates via limited physical access and documentation. Adopts an explicit ethical stance focused on public protection and professional accountability → exemplary answer. | N4: 3 | P4: 3 | R4: 2 | T4: 2 | V4: 3 | X4: 1 | Z4: 2 | AB4: 3 | AD4: 2 | AF4: 2 | AH4: 3
F5: •Do they recognize their professional duties (e.g., safety, honesty, confidentiality, conflict of interest)?
F6: •Do they reference or appropriately relate to a professional code/standard (IEEE, NSPE, ISO, etc.)?
A8: PI42 Make informed judgments considering the impact of engineering solutions in global, societal, economic, and environmental contexts | B8: Demonstrates strong judgment and addresses all four factors (global, societal, economic, environmental) clearly and explicitly when considering the impact of engineering solutions. | C8: Capable of making informed judgments in considering the impact of engineering solutions, but misses at least one applicable factor among global, societal, economic, and environmental contexts. | D8: Demonstrates a basic ability to make informed judgments in considering the impact of engineering solutions, but misses two or more factors in the global, societal, economic, and environmental contexts. | E8: Lacks the ability to make informed judgments in considering the impact of engineering solutions, missing all four factors (global, societal, economic, and environmental contexts). | F8: •Does the student state a clear ethical decision or recommended action? | G8: Positive points: Recognizes need for thorough testing to prevent harm (safety / societal impact). Acknowledges software failure risks and the duty to be honest about limits → good ethical awareness. Mentions societal and environmental benefits (safer, more efficient, environmentally friendly EV system). Missing / weaker parts: Little to no explicit discussion of economic impact or global/cultural contexts. The impacts are stated in a general way, without concrete examples or trade-offs across the four dimensions. | H8: 2 | I8: Positive aspects: Strong ethical framing: obligation to make the system as safe as possible before deployment, including thorough testing in controlled situations. Identifies risk of software defects replacing mechanical links and the potential for harm. Emphasizes duty to be truthful and open about capabilities and constraints. Addresses societal and environmental impact: safer, more energy-efficient, climate-friendly system. What’s missing for the very top level: No explicit mention of economic considerations (cost, affordability, scalability, etc.). Global / cultural context is not clearly discussed (different regulations, user populations, regions, etc.). | J8: 2 | K8: Strong ethical framing: “primary goal is not to harm,” recognition that replacing mechanical links with software introduces risk of software bugs. Emphasizes extensive testing in controlled environments before real use → good safety judgment. Commits to honesty and transparency in reporting capabilities and limitations, with a concrete example (documenting unsupported failure modes and recommending not to operate). Notes positive societal impact (improved safety), environmental impact (climate-friendly, energy-efficient). However: Does not explicitly discuss economic aspects (cost, affordability, scalability) in this answer. Global/cultural context is not clearly articulated (regulations in different regions, different users, etc.). So he clearly makes informed ethical judgments and covers societal and environmental aspects well, but does not fully span all four contexts in this specific response | L8: 2 | M8: Shows safety judgment: choosing to keep mechanical steering/braking as fallback, explaining the trade-off between “advanced” full electronic control and risk in a student prototype. Explicitly balances cost, safety, and mission effectiveness in that decision. Discusses societal benefits: better safety, more efficient energy use. Mentions environmental impact: less impact due to energy-efficient control. Addresses economic impact: lower lifetime service costs by reducing mechanical components. References standards, rules, regulations, and the risk of unsafe deployments without them → clear ethical and professional judgment. Concludes with global framing: cleaner, more safety-conscious, accessible transportation aligned with global engineering needs. He explicitly touches all four contexts (global, societal, economic, environmental) plus ethics and trade-offs | N8: 3 | P8: 3 | R8: 3 | T8: 1 | V8: 3 | X8: 1 | Z8: 2 | AB8: 3 | AD8: 3 | AF8: 1 | AH8: 3
F9: • Is the final judgment consistent with professional integrity and protection of the public?
F10: • Does the student address each GEES factor (global, economic, environmental, societal), or clearly justify why any factor is not applicable?

Sheet SO4 -Assessment Results
A1: SO4 Assessment Results
A2: *Add score 0-3 for each item
A3: SN | B3: Student Name | C3: ID | D3: Project Title For courses without a project, enter N/A | E3: PI41 Recognize | F3: PI42 Judgment | G3: PIs Avg | H3: Attainment | I3: Comments: add comment on the team and individual student performance
A4: 1 | G4: =IF(COUNT(E4:F4)=0,"",AVERAGE(E4:F4)) | H4: =IF(G4="","",IF(G4<1,"BE",IF(G4<2,"DE",IF(G4<3,"ME","AE"))))
A5: 2 | G5: =IF(COUNT(E5:F5)=0,"",AVERAGE(E5:F5)) | H5: =IF(G5="","",IF(G5<1,"BE",IF(G5<2,"DE",IF(G5<3,"ME","AE"))))
A6: 3 | G6: =IF(COUNT(E6:F6)=0,"",AVERAGE(E6:F6)) | H6: =IF(G6="","",IF(G6<1,"BE",IF(G6<2,"DE",IF(G6<3,"ME","AE"))))
A7: 4 | G7: =IF(COUNT(E7:F7)=0,"",AVERAGE(E7:F7)) | H7: =IF(G7="","",IF(G7<1,"BE",IF(G7<2,"DE",IF(G7<3,"ME","AE"))))
A8: 5 | G8: =IF(COUNT(E8:F8)=0,"",AVERAGE(E8:F8)) | H8: =IF(G8="","",IF(G8<1,"BE",IF(G8<2,"DE",IF(G8<3,"ME","AE"))))
A9: 6 | G9: =IF(COUNT(E9:F9)=0,"",AVERAGE(E9:F9)) | H9: =IF(G9="","",IF(G9<1,"BE",IF(G9<2,"DE",IF(G9<3,"ME","AE"))))
A10: 7 | G10: =IF(COUNT(E10:F10)=0,"",AVERAGE(E10:F10)) | H10: =IF(G10="","",IF(G10<1,"BE",IF(G10<2,"DE",IF(G10<3,"ME","AE"))))
A11: 8 | G11: =IF(COUNT(E11:F11)=0,"",AVERAGE(E11:F11)) | H11: =IF(G11="","",IF(G11<1,"BE",IF(G11<2,"DE",IF(G11<3,"ME","AE"))))
A12: 9 | G12: =IF(COUNT(E12:F12)=0,"",AVERAGE(E12:F12)) | H12: =IF(G12="","",IF(G12<1,"BE",IF(G12<2,"DE",IF(G12<3,"ME","AE"))))
A13: 10 | G13: =IF(COUNT(E13:F13)=0,"",AVERAGE(E13:F13)) | H13: =IF(G13="","",IF(G13<1,"BE",IF(G13<2,"DE",IF(G13<3,"ME","AE"))))
A14: 11 | G14: =IF(COUNT(E14:F14)=0,"",AVERAGE(E14:F14)) | H14: =IF(G14="","",IF(G14<1,"BE",IF(G14<2,"DE",IF(G14<3,"ME","AE"))))
A15: 12 | G15: =IF(COUNT(E15:F15)=0,"",AVERAGE(E15:F15)) | H15: =IF(G15="","",IF(G15<1,"BE",IF(G15<2,"DE",IF(G15<3,"ME","AE"))))
... A17: 14 | G17: =IF(COUNT(E17:F17)=0,"",AVERAGE(E17:F17)) | H17: =IF(G17="","",IF(G17<1,"BE",IF(G17<2,"DE",IF(G17<3,"ME","AE"))))
D18: PI Result % | E18: =IFERROR(TEXT((COUNTIF(E4:E17,2)+COUNTIF(E4:E17,3))/COUNT(E4:E17),"0%"),"") | F18: =IFERROR(TEXT((COUNTIF(F4:F17,2)+COUNTIF(F4:F17,3))/COUNT(F4:F17),"0%"),"") | G18: SO Result | H18: =IFERROR(TEXT((COUNTIF(H4:H17,"AE")+COUNTIF(H4:H17,"ME"))/(COUNTIF(H4:H17,"AE")+COUNTIF(H4:H17,"ME")+COUNTIF(H4:H17,"DE")+COUNTIF(H4:H17,"BE")),"0%"),"")
A19: Notes: -PI results are calculated as the percentage of students who achieved a score of 2 or 3. -The SO result is calculated as the percentage of students whose average PI score is 2.0 or higher. -When both project and individual assessments are used, the final PI score is determined based on the combined evidence (average) from both assessments.

Sheet SO4 Assessment Results
C1: Evluation Type | D1: IE | E1: IE
A2: No | B2: ID | C2: Name | D2: PI41 | E2: PI42 | F2: Average | G2: Achievement
D3: 1 | E3: 1 | I3: IE | J3: Individual evaluation
A4: 1 | B4: =IF(#REF!="","",#REF!) -> #REF! | C4: =IF(#REF!="","",#REF!) -> #REF! | D4: {=IF(#REF!="","", INDEX('SO4 Rubric'!$H$4:$ZZ$4, 1, (ROW()-4)*2+1))} -> #REF! | E4: {=IF(#REF!="","", INDEX('SO4 Rubric'!$H$8:$ZZ$8, 1, (ROW()-4)*2+1))} -> #REF! | F4: =IF(SUMPRODUCT(--(D4:E4<>""))=0,"",ROUND(SUMPRODUCT($D$3:$E$3,D4:E4)/COUNTIF($D$3:$E$3,1),0)) -> #REF! | G4: =IF(F4=""," ",VLOOKUP(F4,'Lookup Tables'!$D$9:$E$12,2)) -> #REF!
A5: 2 | B5: =IF(#REF!="","",#REF!) -> #REF! | C5: =IF(#REF!="","",#REF!) -> #REF! | D5: {=IF(#REF!="","", INDEX('SO4 Rubric'!$H$4:$ZZ$4, 1, (ROW()-4)*2+1))} -> #REF! | E5: {=IF(#REF!="","", INDEX('SO4 Rubric'!$H$8:$ZZ$8, 1, (ROW()-4)*2+1))} -> #REF! | F5: =IF(SUMPRODUCT(--(D5:E5<>""))=0,"",ROUND(SUMPRODUCT($D$3:$E$3,D5:E5)/COUNTIF($D$3:$E$3,1),0)) -> #REF! | G5: =IF(F5=""," ",VLOOKUP(F5,'Lookup Tables'!$D$9:$E$12,2)) -> #REF!
A6: 3 | B6: =IF(#REF!="","",#REF!) -> #REF! | C6: =IF(#REF!="","",#REF!) -> #REF! | D6: {=IF(#REF!="","", INDEX('SO4 Rubric'!$H$4:$ZZ$4, 1, (ROW()-4)*2+1))} -> #REF! | E6: {=IF(#REF!="","", INDEX('SO4 Rubric'!$H$8:$ZZ$8, 1, (ROW()-4)*2+1))} -> #REF! | F6: =IF(SUMPRODUCT(--(D6:E6<>""))=0,"",ROUND(SUMPRODUCT($D$3:$E$3,D6:E6)/COUNTIF($D$3:$E$3,1),0)) -> #REF! | G6: =IF(F6=""," ",VLOOKUP(F6,'Lookup Tables'!$D$9:$E$12,2)) -> #REF!
A7: 4 | B7: =IF(#REF!="","",#REF!) -> #REF! | C7: =IF(#REF!="","",#REF!) -> #REF! | D7: {=IF(#REF!="","", INDEX('SO4 Rubric'!$H$4:$ZZ$4, 1, (ROW()-4)*2+1))} -> #REF! | E7: {=IF(#REF!="","", INDEX('SO4 Rubric'!$H$8:$ZZ$8, 1, (ROW()-4)*2+1))} -> #REF! | F7: =IF(SUMPRODUCT(--(D7:E7<>""))=0,"",ROUND(SUMPRODUCT($D$3:$E$3,D7:E7)/COUNTIF($D$3:$E$3,1),0)) -> #REF! | G7: =IF(F7=""," ",VLOOKUP(F7,'Lookup Tables'!$D$9:$E$12,2)) -> #REF!
A8: 5 | B8: =IF(#REF!="","",#REF!) -> #REF! | C8: =IF(#REF!="","",#REF!) -> #REF! | D8: {=IF(#REF!="","", INDEX('SO4 Rubric'!$H$4:$ZZ$4, 1, (ROW()-4)*2+1))} -> #REF! | E8: {=IF(#REF!="","", INDEX('SO4 Rubric'!$H$8:$ZZ$8, 1, (ROW()-4)*2+1))} -> #REF! | F8: =IF(SUMPRODUCT(--(D8:E8<>""))=0,"",ROUND(SUMPRODUCT($D$3:$E$3,D8:E8)/COUNTIF($D$3:$E$3,1),0)) -> #REF! | G8: =IF(F8=""," ",VLOOKUP(F8,'Lookup Tables'!$D$9:$E$12,2)) -> #REF!
A9: 6 | B9: =IF(#REF!="","",#REF!) -> #REF! | C9: =IF(#REF!="","",#REF!) -> #REF! | D9: {=IF(#REF!="","", INDEX('SO4 Rubric'!$H$4:$ZZ$4, 1, (ROW()-4)*2+1))} -> #REF! | E9: {=IF(#REF!="","", INDEX('SO4 Rubric'!$H$8:$ZZ$8, 1, (ROW()-4)*2+1))} -> #REF! | F9: =IF(SUMPRODUCT(--(D9:E9<>""))=0,"",ROUND(SUMPRODUCT($D$3:$E$3,D9:E9)/COUNTIF($D$3:$E$3,1),0)) -> #REF! | G9: =IF(F9=""," ",VLOOKUP(F9,'Lookup Tables'!$D$9:$E$12,2)) -> #REF!
A10: 7 | B10: =IF(#REF!="","",#REF!) -> #REF! | C10: =IF(#REF!="","",#REF!) -> #REF! | D10: {=IF(#REF!="","", INDEX('SO4 Rubric'!$H$4:$ZZ$4, 1, (ROW()-4)*2+1))} -> #REF! | E10: {=IF(#REF!="","", INDEX('SO4 Rubric'!$H$8:$ZZ$8, 1, (ROW()-4)*2+1))} -> #REF! | F10: =IF(SUMPRODUCT(--(D10:E10<>""))=0,"",ROUND(SUMPRODUCT($D$3:$E$3,D10:E10)/COUNTIF($D$3:$E$3,1),0)) -> #REF! | G10: =IF(F10=""," ",VLOOKUP(F10,'Lookup Tables'!$D$9:$E$12,2)) -> #REF!
A11: 8 | B11: =IF(#REF!="","",#REF!) -> #REF! | C11: =IF(#REF!="","",#REF!) -> #REF! | D11: {=IF(#REF!="","", INDEX('SO4 Rubric'!$H$4:$ZZ$4, 1, (ROW()-4)*2+1))} -> #REF! | E11: {=IF(#REF!="","", INDEX('SO4 Rubric'!$H$8:$ZZ$8, 1, (ROW()-4)*2+1))} -> #REF! | F11: =IF(SUMPRODUCT(--(D11:E11<>""))=0,"",ROUND(SUMPRODUCT($D$3:$E$3,D11:E11)/COUNTIF($D$3:$E$3,1),0)) -> #REF! | G11: =IF(F11=""," ",VLOOKUP(F11,'Lookup Tables'!$D$9:$E$12,2)) -> #REF! | H11: =IF(ISBLANK(#REF!),"",IFERROR(ROUND(3*(#REF!/#REF!),0),"")) | I11: =IF(ISBLANK(#REF!),"",IFERROR(ROUND(3*(#REF!/#REF!),0),"")) | J11: =IF(ISBLANK(#REF!),"",IFERROR(ROUND(3*(#REF!/#REF!),0),"")) | K11: =IF(ISBLANK(#REF!),"",IFERROR(ROUND(3*(#REF!/#REF!),0),"")) | L11: =IF(SUMPRODUCT(--(H11:K11<>""))=0,"",SUMPRODUCT(#REF!,H11:K11)/COUNTIF(#REF!,1)) | M11: =IF(L11="","",L11/3)
A12: 9 | B12: =IF(#REF!="","",#REF!) -> #REF! | C12: =IF(#REF!="","",#REF!) -> #REF! | D12: {=IF(#REF!="","", INDEX('SO4 Rubric'!$H$4:$ZZ$4, 1, (ROW()-4)*2+1))} -> #REF! | E12: {=IF(#REF!="","", INDEX('SO4 Rubric'!$H$8:$ZZ$8, 1, (ROW()-4)*2+1))} -> #REF! | F12: =IF(SUMPRODUCT(--(D12:E12<>""))=0,"",ROUND(SUMPRODUCT($D$3:$E$3,D12:E12)/COUNTIF($D$3:$E$3,1),0)) -> #REF! | G12: =IF(F12=""," ",VLOOKUP(F12,'Lookup Tables'!$D$9:$E$12,2)) -> #REF! | H12: =IF(ISBLANK(#REF!),"",IFERROR(ROUND(3*(#REF!/#REF!),0),"")) | I12: =IF(ISBLANK(#REF!),"",IFERROR(ROUND(3*(#REF!/#REF!),0),"")) | J12: =IF(ISBLANK(#REF!),"",IFERROR(ROUND(3*(#REF!/#REF!),0),"")) | K12: =IF(ISBLANK(#REF!),"",IFERROR(ROUND(3*(#REF!/#REF!),0),"")) | L12: =IF(SUMPRODUCT(--(H12:K12<>""))=0,"",SUMPRODUCT(#REF!,H12:K12)/COUNTIF(#REF!,1)) | M12: =IF(L12="","",L12/3)
A13: 10 | B13: =IF(#REF!="","",#REF!) -> #REF! | C13: =IF(#REF!="","",#REF!) -> #REF! | D13: {=IF(#REF!="","", INDEX('SO4 Rubric'!$H$4:$ZZ$4, 1, (ROW()-4)*2+1))} -> #REF! | E13: {=IF(#REF!="","", INDEX('SO4 Rubric'!$H$8:$ZZ$8, 1, (ROW()-4)*2+1))} -> #REF! | F13: =IF(SUMPRODUCT(--(D13:E13<>""))=0,"",ROUND(SUMPRODUCT($D$3:$E$3,D13:E13)/COUNTIF($D$3:$E$3,1),0)) -> #REF! | G13: =IF(F13=""," ",VLOOKUP(F13,'Lookup Tables'!$D$9:$E$12,2)) -> #REF! | H13: =IF(ISBLANK(#REF!),"",IFERROR(ROUND(3*(#REF!/#REF!),0),"")) | I13: =IF(ISBLANK(#REF!),"",IFERROR(ROUND(3*(#REF!/#REF!),0),"")) | J13: =IF(ISBLANK(#REF!),"",IFERROR(ROUND(3*(#REF!/#REF!),0),"")) | K13: =IF(ISBLANK(#REF!),"",IFERROR(ROUND(3*(#REF!/#REF!),0),"")) | L13: =IF(SUMPRODUCT(--(H13:K13<>""))=0,"",SUMPRODUCT(#REF!,H13:K13)/COUNTIF(#REF!,1)) | M13: =IF(L13="","",L13/3)
A14: 11 | B14: =IF(#REF!="","",#REF!) -> #REF! | C14: =IF(#REF!="","",#REF!) -> #REF! | D14: {=IF(#REF!="","", INDEX('SO4 Rubric'!$H$4:$ZZ$4, 1, (ROW()-4)*2+1))} -> #REF! | E14: {=IF(#REF!="","", INDEX('SO4 Rubric'!$H$8:$ZZ$8, 1, (ROW()-4)*2+1))} -> #REF! | F14: =IF(SUMPRODUCT(--(D14:E14<>""))=0,"",ROUND(SUMPRODUCT($D$3:$E$3,D14:E14)/COUNTIF($D$3:$E$3,1),0)) -> #REF! | G14: =IF(F14=""," ",VLOOKUP(F14,'Lookup Tables'!$D$9:$E$12,2)) -> #REF! | H14: =IF(ISBLANK(#REF!),"",IFERROR(ROUND(3*(#REF!/#REF!),0),"")) | I14: =IF(ISBLANK(#REF!),"",IFERROR(ROUND(3*(#REF!/#REF!),0),"")) | J14: =IF(ISBLANK(#REF!),"",IFERROR(ROUND(3*(#REF!/#REF!),0),"")) | K14: =IF(ISBLANK(#REF!),"",IFERROR(ROUND(3*(#REF!/#REF!),0),"")) | L14: =IF(SUMPRODUCT(--(H14:K14<>""))=0,"",SUMPRODUCT(#REF!,H14:K14)/COUNTIF(#REF!,1)) | M14: =IF(L14="","",L14/3)
A15: 12 | B15: =IF(#REF!="","",#REF!) -> #REF! | C15: =IF(#REF!="","",#REF!) -> #REF! | D15: {=IF(#REF!="","", INDEX('SO4 Rubric'!$H$4:$ZZ$4, 1, (ROW()-4)*2+1))} -> #REF! | E15: {=IF(#REF!="","", INDEX('SO4 Rubric'!$H$8:$ZZ$8, 1, (ROW()-4)*2+1))} -> #REF! | F15: =IF(SUMPRODUCT(--(D15:E15<>""))=0,"",ROUND(SUMPRODUCT($D$3:$E$3,D15:E15)/COUNTIF($D$3:$E$3,1),0)) -> #REF! | G15: =IF(F15=""," ",VLOOKUP(F15,'Lookup Tables'!$D$9:$E$12,2)) -> #REF! | H15: =IF(ISBLANK(#REF!),"",IFERROR(ROUND(3*(#REF!/#REF!),0),"")) | I15: =IF(ISBLANK(#REF!),"",IFERROR(ROUND(3*(#REF!/#REF!),0),"")) | J15: =IF(ISBLANK(#REF!),"",IFERROR(ROUND(3*(#REF!/#REF!),0),"")) | K15: =IF(ISBLANK(#REF!),"",IFERROR(ROUND(3*(#REF!/#REF!),0),"")) | L15: =IF(SUMPRODUCT(--(H15:K15<>""))=0,"",SUMPRODUCT(#REF!,H15:K15)/COUNTIF(#REF!,1)) | M15: =IF(L15="","",L15/3)
A16: 13 | B16: =IF(#REF!="","",#REF!) -> #REF! | C16: =IF(#REF!="","",#REF!) -> #REF! | D16: {=IF(#REF!="","", INDEX('SO4 Rubric'!$H$4:$ZZ$4, 1, (ROW()-4)*2+1))} -> #REF! | E16: {=IF(#REF!="","", INDEX('SO4 Rubric'!$H$8:$ZZ$8, 1, (ROW()-4)*2+1))} -> #REF! | F16: =IF(SUMPRODUCT(--(D16:E16<>""))=0,"",ROUND(SUMPRODUCT($D$3:$E$3,D16:E16)/COUNTIF($D$3:$E$3,1),0)) -> #REF! | G16: =IF(F16=""," ",VLOOKUP(F16,'Lookup Tables'!$D$9:$E$12,2)) -> #REF! | H16: =IF(ISBLANK(#REF!),"",IFERROR(ROUND(3*(#REF!/#REF!),0),"")) | I16: =IF(ISBLANK(#REF!),"",IFERROR(ROUND(3*(#REF!/#REF!),0),"")) | J16: =IF(ISBLANK(#REF!),"",IFERROR(ROUND(3*(#REF!/#REF!),0),"")) | K16: =IF(ISBLANK(#REF!),"",IFERROR(ROUND(3*(#REF!/#REF!),0),"")) | L16: =IF(SUMPRODUCT(--(H16:K16<>""))=0,"",SUMPRODUCT(#REF!,H16:K16)/COUNTIF(#REF!,1)) | M16: =IF(L16="","",L16/3)
A17: 14 | B17: =IF(#REF!="","",#REF!) -> #REF! | C17: =IF(#REF!="","",#REF!) -> #REF! | D17: {=IF(#REF!="","", INDEX('SO4 Rubric'!$H$4:$ZZ$4, 1, (ROW()-4)*2+1))} -> #REF! | E17: {=IF(#REF!="","", INDEX('SO4 Rubric'!$H$8:$ZZ$8, 1, (ROW()-4)*2+1))} -> #REF! | F17: =IF(SUMPRODUCT(--(D17:E17<>""))=0,"",ROUND(SUMPRODUCT($D$3:$E$3,D17:E17)/COUNTIF($D$3:$E$3,1),0)) -> #REF! | G17: =IF(F17=""," ",VLOOKUP(F17,'Lookup Tables'!$D$9:$E$12,2)) -> #REF! | H17: =IF(ISBLANK(#REF!),"",IFERROR(ROUND(3*(#REF!/#REF!),0),"")) | I17: =IF(ISBLANK(#REF!),"",IFERROR(ROUND(3*(#REF!/#REF!),0),"")) | J17: =IF(ISBLANK(#REF!),"",IFERROR(ROUND(3*(#REF!/#REF!),0),"")) | K17: =IF(ISBLANK(#REF!),"",IFERROR(ROUND(3*(#REF!/#REF!),0),"")) | L17: =IF(SUMPRODUCT(--(H17:K17<>""))=0,"",SUMPRODUCT(#REF!,H17:K17)/COUNTIF(#REF!,1)) | M17: =IF(L17="","",L17/3)
A18: 15 | B18: =IF(#REF!="","",#REF!) -> #REF! | C18: =IF(#REF!="","",#REF!) -> #REF! | D18: {=IF(#REF!="","", INDEX('SO4 Rubric'!$H$4:$ZZ$4, 1, (ROW()-4)*2+1))} -> #REF! | E18: {=IF(#REF!="","", INDEX('SO4 Rubric'!$H$8:$ZZ$8, 1, (ROW()-4)*2+1))} -> #REF! | F18: =IF(SUMPRODUCT(--(D18:E18<>""))=0,"",ROUND(SUMPRODUCT($D$3:$E$3,D18:E18)/COUNTIF($D$3:$E$3,1),0)) -> #REF! | G18: =IF(F18=""," ",VLOOKUP(F18,'Lookup Tables'!$D$9:$E$12,2)) -> #REF! | H18: =IF(ISBLANK(#REF!),"",IFERROR(ROUND(3*(#REF!/#REF!),0),"")) | I18: =IF(ISBLANK(#REF!),"",IFERROR(ROUND(3*(#REF!/#REF!),0),"")) | J18: =IF(ISBLANK(#REF!),"",IFERROR(ROUND(3*(#REF!/#REF!),0),"")) | K18: =IF(ISBLANK(#REF!),"",IFERROR(ROUND(3*(#REF!/#REF!),0),"")) | L18: =IF(SUMPRODUCT(--(H18:K18<>""))=0,"",SUMPRODUCT(#REF!,H18:K18)/COUNTIF(#REF!,1)) | M18: =IF(L18="","",L18/3)
A19: 16 | B19: =IF(#REF!="","",#REF!) -> #REF! | C19: =IF(#REF!="","",#REF!) -> #REF! | D19: {=IF(#REF!="","", INDEX('SO4 Rubric'!$H$4:$ZZ$4, 1, (ROW()-4)*2+1))} -> #REF! | E19: {=IF(#REF!="","", INDEX('SO4 Rubric'!$H$8:$ZZ$8, 1, (ROW()-4)*2+1))} -> #REF! | F19: =IF(SUMPRODUCT(--(D19:E19<>""))=0,"",ROUND(SUMPRODUCT($D$3:$E$3,D19:E19)/COUNTIF($D$3:$E$3,1),0)) -> #REF! | G19: =IF(F19=""," ",VLOOKUP(F19,'Lookup Tables'!$D$9:$E$12,2)) -> #REF! | H19: =IF(ISBLANK(#REF!),"",IFERROR(ROUND(3*(#REF!/#REF!),0),"")) | I19: =IF(ISBLANK(#REF!),"",IFERROR(ROUND(3*(#REF!/#REF!),0),"")) | J19: =IF(ISBLANK(#REF!),"",IFERROR(ROUND(3*(#REF!/#REF!),0),"")) | K19: =IF(ISBLANK(#REF!),"",IFERROR(ROUND(3*(#REF!/#REF!),0),"")) | L19: =IF(SUMPRODUCT(--(H19:K19<>""))=0,"",SUMPRODUCT(#REF!,H19:K19)/COUNTIF(#REF!,1)) | M19: =IF(L19="","",L19/3)
A20: 17 | B20: =IF(#REF!="","",#REF!) -> #REF! | C20: =IF(#REF!="","",#REF!) -> #REF! | D20: {=IF(#REF!="","", INDEX('SO4 Rubric'!$H$4:$ZZ$4, 1, (ROW()-4)*2+1))} -> #REF! | E20: {=IF(#REF!="","", INDEX('SO4 Rubric'!$H$8:$ZZ$8, 1, (ROW()-4)*2+1))} -> #REF! | F20: =IF(SUMPRODUCT(--(D20:E20<>""))=0,"",ROUND(SUMPRODUCT($D$3:$E$3,D20:E20)/COUNTIF($D$3:$E$3,1),0)) -> #REF! | G20: =IF(F20=""," ",VLOOKUP(F20,'Lookup Tables'!$D$9:$E$12,2)) -> #REF! | H20: =IF(ISBLANK(#REF!),"",IFERROR(ROUND(3*(#REF!/#REF!),0),"")) | I20: =IF(ISBLANK(#REF!),"",IFERROR(ROUND(3*(#REF!/#REF!),0),"")) | J20: =IF(ISBLANK(#REF!),"",IFERROR(ROUND(3*(#REF!/#REF!),0),"")) | K20: =IF(ISBLANK(#REF!),"",IFERROR(ROUND(3*(#REF!/#REF!),0),"")) | L20: =IF(SUMPRODUCT(--(H20:K20<>""))=0,"",SUMPRODUCT(#REF!,H20:K20)/COUNTIF(#REF!,1)) | M20: =IF(L20="","",L20/3)
A21: 18 | B21: =IF(#REF!="","",#REF!) -> #REF! | C21: =IF(#REF!="","",#REF!) -> #REF! | D21: {=IF(#REF!="","", INDEX('SO4 Rubric'!$H$4:$ZZ$4, 1, (ROW()-4)*2+1))} -> #REF! | E21: {=IF(#REF!="","", INDEX('SO4 Rubric'!$H$8:$ZZ$8, 1, (ROW()-4)*2+1))} -> #REF! | F21: =IF(SUMPRODUCT(--(D21:E21<>""))=0,"",ROUND(SUMPRODUCT($D$3:$E$3,D21:E21)/COUNTIF($D$3:$E$3,1),0)) -> #REF! | G21: =IF(F21=""," ",VLOOKUP(F21,'Lookup Tables'!$D$9:$E$12,2)) -> #REF! | H21: =IF(ISBLANK(#REF!),"",IFERROR(ROUND(3*(#REF!/#REF!),0),"")) | I21: =IF(ISBLANK(#REF!),"",IFERROR(ROUND(3*(#REF!/#REF!),0),"")) | J21: =IF(ISBLANK(#REF!),"",IFERROR(ROUND(3*(#REF!/#REF!),0),"")) | K21: =IF(ISBLANK(#REF!),"",IFERROR(ROUND(3*(#REF!/#REF!),0),"")) | L21: =IF(SUMPRODUCT(--(H21:K21<>""))=0,"",SUMPRODUCT(#REF!,H21:K21)/COUNTIF(#REF!,1)) | M21: =IF(L21="","",L21/3)
A22: 19 | B22: =IF(#REF!="","",#REF!) -> #REF! | C22: =IF(#REF!="","",#REF!) -> #REF! | D22: {=IF(#REF!="","", INDEX('SO4 Rubric'!$H$4:$ZZ$4, 1, (ROW()-4)*2+1))} -> #REF! | E22: {=IF(#REF!="","", INDEX('SO4 Rubric'!$H$8:$ZZ$8, 1, (ROW()-4)*2+1))} -> #REF! | F22: =IF(SUMPRODUCT(--(D22:E22<>""))=0,"",ROUND(SUMPRODUCT($D$3:$E$3,D22:E22)/COUNTIF($D$3:$E$3,1),0)) -> #REF! | G22: =IF(F22=""," ",VLOOKUP(F22,'Lookup Tables'!$D$9:$E$12,2)) -> #REF! | H22: =IF(ISBLANK(#REF!),"",IFERROR(ROUND(3*(#REF!/#REF!),0),"")) | I22: =IF(ISBLANK(#REF!),"",IFERROR(ROUND(3*(#REF!/#REF!),0),"")) | J22: =IF(ISBLANK(#REF!),"",IFERROR(ROUND(3*(#REF!/#REF!),0),"")) | K22: =IF(ISBLANK(#REF!),"",IFERROR(ROUND(3*(#REF!/#REF!),0),"")) | L22: =IF(SUMPRODUCT(--(H22:K22<>""))=0,"",SUMPRODUCT(#REF!,H22:K22)/COUNTIF(#REF!,1)) | M22: =IF(L22="","",L22/3)
A23: 20 | B23: =IF(#REF!="","",#REF!) -> #REF! | C23: =IF(#REF!="","",#REF!) -> #REF! | D23: {=IF(#REF!="","", INDEX('SO4 Rubric'!$H$4:$ZZ$4, 1, (ROW()-4)*2+1))} -> #REF! | E23: {=IF(#REF!="","", INDEX('SO4 Rubric'!$H$8:$ZZ$8, 1, (ROW()-4)*2+1))} -> #REF! | F23: =IF(SUMPRODUCT(--(D23:E23<>""))=0,"",ROUND(SUMPRODUCT($D$3:$E$3,D23:E23)/COUNTIF($D$3:$E$3,1),0)) -> #REF! | G23: =IF(F23=""," ",VLOOKUP(F23,'Lookup Tables'!$D$9:$E$12,2)) -> #REF! | H23: =IF(ISBLANK(#REF!),"",IFERROR(ROUND(3*(#REF!/#REF!),0),"")) | I23: =IF(ISBLANK(#REF!),"",IFERROR(ROUND(3*(#REF!/#REF!),0),"")) | J23: =IF(ISBLANK(#REF!),"",IFERROR(ROUND(3*(#REF!/#REF!),0),"")) | K23: =IF(ISBLANK(#REF!),"",IFERROR(ROUND(3*(#REF!/#REF!),0),"")) | L23: =IF(SUMPRODUCT(--(H23:K23<>""))=0,"",SUMPRODUCT(#REF!,H23:K23)/COUNTIF(#REF!,1)) | M23: =IF(L23="","",L23/3)
D24: PI Results | F24: SO Result | G24: BE | H24: =COUNTIF('SO4 Assessment Results'!$G$4:$G$23,G24) -> 0 | I24: =IFERROR(TEXT(((H26+H27)/SUM(H24:H27)),"0%"),"")
D25: PI41 | E25: PI42 | G25: DE | H25: =COUNTIF('SO4 Assessment Results'!$G$4:$G$23,G25) -> 0
D26: =IFERROR(AVERAGE(D4:D20),"") | E26: =IFERROR(AVERAGE(E4:E20),"") | G26: ME | H26: =COUNTIF('SO4 Assessment Results'!$G$4:$G$23,G26) -> 0 | K26: =IFERROR(AVERAGE(K11:K23),"")
D27: =IFERROR(TEXT((COUNTIF(D4:D23,2) + COUNTIF(D4:D23,3)) / COUNT(D4:D23),"0%"),"") | E27: =IFERROR(TEXT((COUNTIF(E4:E23,2) + COUNTIF(E4:E23,3)) / COUNT(E4:E23),"0%"),"") | G27: AE | H27: =COUNTIF('SO4 Assessment Results'!$G$4:$G$23,G27) -> 0
B30: Comment on the PIs results if any is below 2 or if the SO is below 70%
B31: All PIs and the SO results are above the threshold

Sheet Student work Description
A1: Student Work Description
A3: SO - PI | B3: Assessment Item | D3: Questions Used | N3: Justification of assessment item selection
A4: =#REF! -> #REF! | B4: =IF(#REF!=0,"",#REF! & " - " &#REF!) -> #REF!
A5: =#REF! -> #REF! | B5: =IF(#REF!=0,"",#REF! & " - " &#REF!) -> #REF!
A6: =#REF! -> #REF! | B6: =IF(#REF!=0,"",#REF! & " - " &#REF!) -> #REF!
A7: =#REF! -> #REF! | B7: =IF(#REF!=0,"",#REF! & " - " &#REF!) -> #REF!
A8: =#REF! -> #REF! | B8: =IF(#REF!=0,"",#REF! & " - " &#REF!) -> #REF!
A9: =#REF! -> #REF! | B9: =IF(#REF!=0,"",#REF! & " - " &#REF!) -> #REF!
A10: =#REF! -> #REF! | B10: =IF(#REF!=0,"",#REF! & " - " &#REF!) -> #REF!
A11: =#REF! -> #REF! | B11: =IF(#REF!=0,"",#REF! & " - " &#REF!) -> #REF!
A12: =#REF! -> #REF! | B12: =IF(#REF!=0,"",#REF! & " - " &#REF!) -> #REF!
A13: =#REF! -> #REF! | B13: =IF(#REF!=0,"",#REF! & " - " &#REF!) -> #REF!
A14: =#REF! -> #REF! | B14: =IF(#REF!=0,"",#REF! & " - " &#REF!) -> #REF!
A15: =#REF! -> #REF! | B15: =IF(#REF!=0,"",#REF! & " - " &#REF!) -> #REF!

Sheet SO4
B3: Key Performance Indicators and Rubrics for Student Outcome:
B4: 4. Recognize professional responsibilities and make informed judgments in computing practice based on legal and ethical principles.
B5: KPI Nbr. | C5: KPI Definition | D5: Level 0: Below Expectation (BE) | E5: Level 1: Developing Expectation (DE) | F5: Level 2: Meet Expectation (ME) | G5: Level 3: Above Expectation (AE)
B6: 4.1 | C6: Demonstrate ability to recognize impact and determine best practices. | D6: Little recognition of the impact of computing practices on individuals, organizations and society. | E6: Some recognition of the effects of computing practices on individuals, organizations and society, but little demonstrated ability to determine best practices. | F6: Recognizes some effects of computing practices onindividuals, organizations and society, and demonstrates acceptable ability to determine best practices | G6: Recognizes the effects of computing practices on individuals, organization, and society and demonstrates good ability to determine good practices
B7: 4.2 | C7: Demonstrates an ability to recognize ethical dilemmas and apply professional ethical practices to make appropriate decisions | D7: Needs assistance to identify ethical dilemmas and to apply the code of ethics from professional societies and/or ethical theories | E7: Demonstrates some ability to identify ethical dilemmas and is aware of, but cannot necessarily apply, a professional code of ethics and/or ethical theory | F7: Demonstrates acceptable ability to identify ethical dilemmas and recognizes basic elements of a professional code of ethics and/or ethical theory | G7: Can apply elements from a professional code of ethics and/or ethical theory to recognize ethical dilemmas and analyze them.

Sheet SO5
B3: Key Performance Indicators and Rubrics for Student Outcome:
B4: 5. Function effectively as a member or leader of a team engaged in activities appropriate to the program’s discipline.
B5: KPI Nbr. | C5: KPI Definition | D5: Level 0: Below Expectation (BE) | E5: Level 1: Developing Expectation (DE) | F5: Level 2: Meet Expectation (ME) | G5: Level 3: Above Expectation (AE)
B6: 4.1 | C6: Actively contributes to the classroom learning environment with interest, passion , and curiosity | D6: Appears uninterested and does not demonstrate or share curiosity and passion. Is defensive about feedback and suggestions. | E6: Show some interest. Rarely to ask questions and seeks information related to instruction and classroom practice. | F6: Demonstrates interest, passion, and curiosity. Asks questions and seeks information related to instruction and classroom practice. Willingly incorporates suggestions and responds appropriately to feedback. | G6: Openly contributes to the classroom learning environment as a result of their interest, passion, and curiosity.
B7: 4.2 | C7: Effeciently collects information and propose ideas to the team relevant to the group purpose | D7: Does not collect any relevant information; no useful suggestions to address team's needs. | E7: Participates in collecting general information related to the project; Do not share useful ideas to meet the team's needs. | F7: Collects basic, useful information related to the project; occasionally offers useful ideas to meet the team's needs. | G7: Collects and presents to the team a great deal of relevant information; offers welldeveloped and clearly expressed ideas directly related to the group's purpose
B8: 4.3 | C8: Participate actively all team groups and effectively conduct all assigned tasks | D8: Does not perform assigned tasks; often misses meetings and, when present, does not have anything constructive to say; relies on others to do the work. | E8: Performs some assigned tasks; miss some meetings,contributes rarely to the team work. | F8: Performs all assigned tasks; attends meetings regularly and usually participates effectively; generally reliable. | G8: Performs all tasks very effectively; attends all meetings and participates enthusiastically; very reliable.
B9: 4.4 | C9: Able as leader to to accept other team members' ideas and contribute to their development and give them full credit | D9: Often argues with team mates; doesn't let anyone else talk; occasional personal attacks and "put-downs"; wants to have things done his way and does not listen to alternate approaches. | E9: Sometimes listens to others' points of view but do not make effort to understands other ideas. | F9: Generally listens to others' points of view; always uses appropriate and respectful language; tries to make a definite effort to understand others' ideas. | G9: Always listens to others and their ideas; helps them develop their ideas while giving them full credit; always helps the team reach a fair decision.

Sheet SO6
B3: Key Performance Indicators and Rubrics for Student Outcome:
B4: 6. Support the delivery, use, and management of information systems within an information systems environment.
B5: KPI Nbr. | C5: KPI Definition | D5: Level 0: Below Expectation (BE) | E5: Level 1: Developing Expectation (DE) | F5: Level 2: Meet Expectation (ME) | G5: Level 3: Above Expectation (AE)
B6: 6.1 | C6: Recall and understand the fundamental of business concepts (i.e. marketing, accounting, human resource, etc.), its environment, and requirements | D6: Unable to understand business processes and requirements | E6: Recall some business process concepts without being able to apply them | F6: Recall and understands some business concepts and properly apply them | G6: Understands and able to properly analyse a business process in a given context and apply them
B7: 6.2 | C7: Correctly apply the the understanding of business processes and environment (i.e. marketing, finance, etc.), for developing relevant information system solutions to solve business problems | D7: Unable to apply and develop any system based on the fundamental related concept in business. | E7: Able to partially apply and develop any system based on the fundamental related concept in business. | F7: Able to show satisfactory application of business concept and develop any system based on the fundamental related concept in business. | G7: able to successfully apply business concept and develop any system based on the fundamental related concept in business.
B8: 6.3 | C8: Evaluate and relates the differences in business functions (i.e. marketing, finance, accounting, etc.) and related entities (people and processes) within the business environment, for getting user requirement and customization of IS solutions (i.e. ERP) | D8: Unable to identify and differentiate users and their roles in various different functions in the business to create requirements, and perform any customization to IS solution. | E8: Can identify and differentiate some parts of the user requirements but cannot customize the IS solution properly | F8: Can identify and differentiate most of the business user requirements and functions, and customize the IS solution satisfactorily | G8: Can successfully identify business user requirements, customize and deliver successfully the IS solution
B9: 6.4 | C9: Identify and evaluate IS technologies and business solutions (DBMS, ERP, etc) by applying knowledge of the business environment and its functional areas (management, marketing, etc.) | D9: Unable to identify and evaluate any IS solution related to any business concepts and environment | E9: Able to partially identify and evaluate IS solution related to some concepts in the business environment | F9: Able to identify and evaluate satisfactorily IS solution related to some concepts in the business environment | G9: Able to identify and evaluate successfully IS solution by effectively relating to all concepts in the business environment

Sheet SO7
B3: Key Performance Indicators and Rubrics for Student Outcome:
B4: 7. Develop and evaluate E-commerce systems on different platforms using a variety of technologies.
B5: KPI Nbr. | C5: KPI Definition | D5: Level 0: Below Expectation (BE) | E5: Level 1: Developing Expectation (DE) | F5: Level 2: Meet Expectation (ME) | G5: Level 3: Above Expectation (AE)
B6: 7.1 | C6: Properly design and develop E-commerce solutions | D6: Cannot recognize E-commerce solution development process | E6: Partially recall the phases of the development of E-commerce solutions | F6: Fully describe the process for the development of E-commerce solution without being able to apply it properly | G6: Successfully design and develop E-commerce Solution
B7: 7.2 | C7: Accurately compare and evaluate E-Commerce systems | D7: Do not recall the criteria for evaluating and comparing E-commerce solutions | E7: Recognize some of the criteria for the evaluation of E-commerce solutions | F7: Recall all the criteria for the evaluation and the comparison of E-commerce systems | G7: Successfully compare and evaluate E-commerce systems
B8: 7.3 | C8: Successfully implement E-commerce solutions on different platforms | D8: Recognize the need for using E-commerce development platforms | E8: Cite different E-commerce development platforms | F8: Partially use at least one E-commerce development plateform | G8: Conveniently use a different platforms for developing E-commerce solutions
B9: 7.4 | C9: Successfully use different technologies to develop E-commerce solutions | D9: Unable to enumerate some e-commerce development techologies | E9: Cite and partially define the usefullness of some E-commerce development technologies | F9: Partially use some E-commerce development technologies to develop relevent solutions | G9: Fully understand and use different E-commerce development technologies to deliver E-commerce solutions

Sheet SO8
B4: Rubrics for Student Outcome 8
B5: CYS-SO Apply security principles and practices to the environment , hardware, social and human aspects of a system
C6: Criterion | D6: Assessment of Criterion
D7: Above Expectation | E7: Meeting expectation | F7: Developing Expectation | G7: Below Expectation
D8: 3 | E8: 2 | F8: 1 | G8: 0
B9: 8.1 | C9: Describe security as a continuous process of tradeoffs, balancing between protection mechanisms and availability | D9: Students are able to Illustrate security as a continuous process of tradeoffs, balancing between protection mechanisms and availability. | E9: Students are able to describe security as a continuous process of tradeoffs, balancing between protection mechanisms and availability. | F9: Students are able to recognize the importance of security as a continuous process of tradeoffs. | G9: Students are not able to recognize the importance of security as a continuous process of tradeoffs.
B10: 8.2 | C10: Analyze the tradeoffs of balancing key security properties, including Confidentiality, Integrity, and Availability (CIA). | D10: Students are able to evaluate the tradeoffs of balancing key security properties, including Confidentiality, Integrity, and Availability (CIA). | E10: Students are able to analyze the tradeoffs of balancing key security properties, including Confidentiality, Integrity, and Availability (CIA) | F10: Students are able to investigate the tradeoffs of balancing key security properties, including Confidentiality, Integrity, and Availability (CIA) | G10: Students are not able to investigate the tradeoffs of balancing key security properties, including Confidentiality, Integrity, and Availability (CIA)
B11: 8.3 | C11: Illustrate through examples the concepts of security and privacy risk, threats, vulnerabilities, attack vectors, and exploits, noting there is no such thing as perfect security. | D11: Students are able to compare the concepts of risk, threats, vulnerabilities, attack vectors, and exploits to a given scenario. | E11: Students are able to illustrate through examples the concepts of risk, threats, vulnerabilities, attack vectors, and exploits, noting there is no such thing as perfect security. | F11: Students are able to differentiate the concepts of risk, threats, vulnerabilities, attack vectors, and exploits. | G11: Students are notable to differentiate the concepts of risk, threats, vulnerabilities, attack vectors, and exploits.
B13: 8.4 | C13: Apply security principles and practices for secure software development in a dynamic environment | D13: Students are able to examine security principles and practices for secure software development in a dynamic environment. | E13: Students are able to apply security principles and practices for secure software development in a dynamic environment. | F13: Students are able to summarize security principles and practices for secure software development. | G13: Students are not able to summarize security principles and practices for secure software development.

Sheet Lookup Tables
L1: SO1 | M1: Ability to identify, formulate, and solve complex engineering problems by applying principles of engineering, science, and mathematics.
L2: SO2 | M2: An ability to apply engineering design to produce solutions that meet specified needs with consideration of public health, safety, and welfare, as well as global, cultural, social, environmental, and economic factors.
L3: SO3 | M3: An ability to communicate effectively with a range of audiences.
L4: SO4 | M4: An ability to recognize ethical and professional responsibilities in engineering situations and make informed judgments, which must consider the impact of engineering solutions in global, economic, environmental, and societal contexts.
L5: SO5 | M5: An ability to function effectively on a team whose members together provide leadership, create a collaborative and inclusive environment, establish goals, plan tasks, and meet objectives.
L6: SO6 | M6: An ability to develop and conduct appropriate experimentation, analyze and interpret data, and use engineering judgment to draw conclusions
L7: SO7 | M7: An ability to acquire and apply new knowledge as needed, using appropriate learning strategies.
D8: Student's Satisfaction
C9: 0 | D9: 0 | E9: BE | F9: Below Expextations
C10: 1 | D10: 1 | E10: DE | F10: Developing Expectation
C11: 2 | D11: 2 | E11: ME | F11: Meets Expectations
C12: 3 | D12: 3 | E12: AE | F12: Accomplished Expectations | L12: Quiz
L13: Major
L14: Final
H15: 0 | I15: 0 | L15: Project
H16: 1 | I16: 1 | L16: Assignment
I17: 2
D18: Section's Satisfaction | I18: 3
D19: 59 | E19: BE | F19: Less than 60% of students are achieving the Satisfactory level (ME) or above
D20: 69 | E20: DE | F20: 60% to 69% of students are achieving the Satisfactory level (ME) or above
D21: 84 | E21: ME | F21: 70% to 79% of students are achieving the Satisfactory level (ME) or above
D22: 100 | E22: AE | F22: 90% or more of students are achieving the Satisfactory level (ME) or above
