Workbook
Name OutcomesList: '[1]Lookups Tables'!$J$3:$J$12
Name Percentage: '[1]Lookups Tables'!$L$4:$L$23

Sheet Main
A1: Course Name: | F1: Semester:
A2: Course Code: | F2: Instructor:
A4: SO | F4: Mapped PIs | J4: Mapped CLO
A5: SO2 | B5: =VLOOKUP(A5,'Lookup Tables'!$L$1:$M$7,2,FALSE) -> An ability to apply engineering design to produce solutions that meet specified needs with consideration of public health, safety, and welfare, as well as global, cultural, social, environmental, and economic factors. | F5: PI21 Apply engineering design to produce a solution that meets specified needs PI22 Design Solutions that consider public health, safety, and welfare, as well as global, cultural, social, environmental, and economic factors PI23 Identify and Justifymultiple realistic constraints relevant to the project design PI 24 Identify and Apply appropriate engineering standards and codes relevant to the project design | J5: Add the CLO mapaped to this SO
A6: SO4 | B6: =VLOOKUP(A6,'Lookup Tables'!$L$1:$M$7,2,FALSE) -> An ability to recognize ethical and professional responsibilities in engineering situations and make informed judgments, which must consider the impact of engineering solutions in global, economic, environmental, and societal contexts. | F6: PI41 Recognize ethical and professional responsibilities in engineering situations PI42 Make informed judgments considering the impact of engineering solutions in global, societal, economic, and environmental contexts | J6: 3.1 Recognize the engineering profession and the importance of ethical and legal factors in professional duties
A8: Please provide the information below to support the preparation of the Student Outcome assessment report.
A9: Assessment type | C9: Design factors | F9: Justification of the assessment selection (mention how it is related the PIs of the SO2)
A10: [List all assessment instruments used to assess the students for this SO. Mention those are team based and those are invidual } e.g., Team based: -final design report, -presentation -prototype demonstration individaul assssment: -individual oral defense, -oral presentation discussion, -assignment, - final-exam question. ] | C10: [List all relevant design factors considered by the students in the project. Include only the factors that were actually addressed]. e.g., -Public Health, -Safety -Welfare; - Global; -Cultural; -Social; -Environmental; -Economic. If you have more than one project, mention which covered in project x and which covered in project y in case they are different] | F10: [Add brief description for how the assessment addressed each PI. See the example below. Below is an example for radar system project] PI 21: The assessment is about designing a radar system to meet specified needs and performance requirements within realistic constraints. It requires students to define the required system performance, develop a suitable design solution, select and calculate the necessary radar parameters, and make engineering decisions based on analysis and trade-offs. The proposed design must then be evaluated to verify that it satisfies the stated requirements, specifications, and constraints, consistent with the ABET definition of engineering design as an iterative decision-making process for developing solutions to meet desired needs and specifications. PI 22: The assessment requires the radar design to consider relevant safety, environmental, and economic factors and to incorporate these considerations into the selection of the system configuration and parameters. PI 23: The assessment requires the considering multiple realistic design constraints, such as available transmit power, antenna size, bandwidth, cost, and hardware limitations, and consideration of their impact on the radar design. PI 24: The assessment requires the use of ETSI EN 301 091-1 for the vehicular radar design. The assessment specifies that the radar operating frequency must be selected within the 76–77 GHz band, and the selected transmitter and antenna parameters must satisfy the applicable transmitted-power limits, including a maximum peak EIRP of 55 dBm. These standard-based parameters are incorporated as design requirements that must be considered when selecting the radar operating frequency, transmit power, and antenna characteristics.
A11: Verion | C11: 2
A12: Date of update | C12: 47024

Sheet SO2-PI21 Rubric
A1: PI21 Assessment Rubric
A2: Assessment item | B2: Above Expectation (3) | C2: Meet Expectation (2) | D2: Developing Expectation (1) | E2: Below Expectation (0) | F2: Checklist for Assessment
A4: 1. Problem, Needs & Requirements | B4: Clearly defines the problem, needs, requirements, and relevant stakeholders. | C4: Defines the problem, needs, requirements, and relevant stakeholders. | D4: Defines some elements, but they are incomplete or unclear. | E4: Problem, needs, requirements, or stakeholders are missing or incorrect. | F4: Team assessment (Report): • Is the problem clearly defined? • Are the needs, requirements, and relevant stakeholders identified? Individual Assessment: • Explain the main problem and identify one key requirement that influenced the design.
A5: 2. System / Component / Process Design | B5: Develops a clear and well-structured design that fully addresses the requirements. | C5: Develops an appropriate design that addresses the main requirements. | D5: Develops a partial or unclear design with limited connection to requirements. | E5: Design is incomplete, inappropriate, or does not address the requirements. | F5: Team assessment (Report): • Is an appropriate system, component, or process designed? • Does the design address the specified requirements? Individual Assessment: • Explain one important design decision and why it was selected.
A6: 3. Alternatives & Creativity | B6: Develops and compares multiple feasible alternatives and clearly justifies the selected solution. | C6: Develops feasible alternatives and provides justification for the selected solution. | D6: Considers limited alternatives with weak comparison or justification. | E6: No meaningful alternatives are considered. | F6: Team assessment (Report): • Are feasible alternatives considered and compared? • Is the selected solution justified? Individual Assessment: • Identify one alternative considered and explain why it was not selected.
A7: 4. Application of Engineering, Science & Mathematics | B7: Correctly applies relevant engineering, science, and mathematics principles and clearly uses the results to support design decisions. | C7: Correctly applies relevant engineering, science, and mathematics principles to support the design. | D7: Applies some relevant principles, but with gaps or limited connection to the design. | E7: Principles are missing, incorrect, or not meaningfully applied. | F7: Team assessment (Report): • Are relevant engineering, science, and mathematics principles correctly applied? • Are the results used to support the design? Individual Assessment (Oral Discussion): • Explain one principle used in the design and how it supported a design decision.
A8: 5. Analysis & System Integration | B8: Performs appropriate analysis and clearly demonstrates how system elements work together. | C8: Performs appropriate analysis and shows how the main system elements work together. | D8: Analysis or integration is limited or only partially demonstrated. | E8: Analysis is inadequate or system integration is not demonstrated. | F8: Team assessment (Report): • Is appropriate analysis performed? • Is it clear how the main elements work together? Individual Assessment: • Explain how one part of the design interacts with or affects another part.
A9: 6. Evaluation Against Requirements | B9: Evaluates the design against the requirements and clearly explains results, limitations, or unmet requirements. | C9: Evaluates the design against the main requirements. | D9: Evaluates only some requirements or provides limited evidence. | E9: The design is not meaningfully evaluated against the requirements. | F9: Team assessment (Report): • Is the design evaluated against the specified requirements? • Are results or limitations discussed? Individual Assessment: • Identify one requirement and explain how the design was evaluated against it.
A10: 7. Risks & Trade-offs | B10: Identifies relevant risks and clearly explains important trade-offs and their influence on design decisions. | C10: Identifies relevant risks and considers important trade-offs in the design. | D10: Identifies some risks or trade-offs, but discussion is limited. | E10: Risks and trade-offs are missing or not considered. | F10: Team assessment (Report): • Are relevant risks identified? • Are important trade-offs considered in design decisions? Individual Assessment: • Identify one risk or trade-off and explain how it affected the design.
A11: 8. Iteration & Improvement | B11: Uses evaluation, testing, or feedback to make and clearly justify meaningful design improvements. | C11: Uses evaluation, testing, or feedback to improve the design. | D11: Makes limited improvements with weak connection to evaluation, testing, or feedback. | E11: No meaningful design iteration or improvement is demonstrated. | F11: Team assessment (Report): • Is the design improved based on evaluation, testing, or feedback? • Are the improvements justified? Individual Assessment: • Describe one change made to the design and explain why it was made.
A12: Assessment Note: • Team-based assessment is based on team evidence (e.g., final report). • Individual attainment may be verified through structured oral questions or individual exam questions.

Sheet SO2-PI22,PI23&PI24 Rubric
A1: PI22, PI23, and PI24 Assessment Rubric
A2: Assessment item | B2: Above Expectation (3) | C2: Meet Expectation (2) | D2: Developing Expectation (1) | E2: Below Expectation (0) | F2: Checklist for Assessment
A4: PI22 Design Solutions that consider public health, safety, and welfare, as well as global, cultural, social, environmental, and economic factors | B4: The design considers relevant factors such as public health, safety, welfare, global, cultural, social, environmental, and economic factors, and clearly explains how they influence design decisions. | C4: The design considers relevant factors such as public health, safety, welfare, global, cultural, social, environmental, and economic factors. | D4: Considers some relevant factors, but their connection to the design is limited or unclear. | E4: Relevant factors are not adequately considered in the design. | F4: Team assessment (Report): • Does the design consider relevant factors such as public health, safety, welfare, global, cultural, social, environmental, and economic factors? • Does the report explain how the relevant factors influence design decisions? Individual Assessment: • Identify one relevant factor considered in the design and explain how it influenced a design decision.
A5: PI23 Identifies and justifies multiple realistic constraints relevant to the project design | B5: Identifies and justifies multiple relevant constraints and clearly explains their impact on design decisions and trade-offs. | C5: Identifies relevant constraints and explains their impact on key design decisions. | D5: Identifies some constraints, but justification or connection to design decisions is limited. | E5: Constraints are missing, incorrect, or not linked to design decisions. | F5: Team assessment (Report): • Are relevant constraints identified and, where appropriate, quantified? • Do the constraints influence design decisions or trade-offs? Individual assessment: • Identify one important constraint and explain how it affected a specific design decision.
A6: PI 24 Identifies and applies appropriate engineering standards and codes relevant to the project design | B6: Identifies relevant standards/codes, applies them to the design, and clearly explains how they guide design decisions. | C6: Identifies relevant standards/codes and applies them to the design. | D6: Identifies some standards/codes, but their application to the design is limited. | E6: Relevant standards/codes are missing, incorrect, or not applied to the design. | F6: Team assessment (Report): •Are relevant standards/codes identified? •Are they applied to guide design decisions or parameters? Individual assessment: • Identify one standard/code used and explain how it affected a specific design decision or parameter.
A7: Assessment Note: • Team-based assessment is based on team evidence (e.g., final report). • Individual attainment may be verified through structured oral questions, individual exam questions, individual reflection.

Sheet SO4 Rubric
A1: SO4 Rubric
A2: Assessment item | B2: Above | C2: Meet | D2: Developing | E2: Below | F2: Checklist for Assessment | G2: ="ID# " &#REF! -> #REF! | I2: ="ID# " &#REF! -> #REF! | K2: ="ID# " &#REF! -> #REF! | M2: ="ID# " &#REF! -> #REF! | O2: ="ID# " &#REF! -> #REF! | Q2: ="ID# " &#REF! -> #REF! | S2: ="ID# " &#REF! -> #REF! | U2: ="ID# " &#REF! -> #REF! | W2: ="ID# " &#REF! -> #REF! | Y2: ="ID# " &#REF! -> #REF! | AA2: ="ID# " &#REF! -> #REF! | AC2: ="ID# " &#REF! -> #REF! | AE2: ="ID# " &#REF! -> #REF! | AG2: ="ID# " &#REF! -> #REF!
B3: Expectation (3) | C3: Expectation (2) | D3: Expectation (1) | E3: Expectation (0) | G3: Comment | H3: score (0-3) | I3: Comment | J3: score (0-3) | K3: Comment | L3: score (0-3) | M3: Comment | N3: score (0-3) | O3: Comment | P3: score (0-3) | Q3: Comment | R3: score (0-3) | S3: Comment | T3: score (0-3) | U3: Comment | V3: score (0-3) | W3: Comment | X3: score (0-3) | Y3: Comment | Z3: score (0-3) | AA3: Comment | AB3: score (0-3) | AC3: Comment | AD3: score (0-3) | AE3: Comment | AF3: score (0-3) | AG3: Comment | AH3: score (0-3)
A4: PI41. Recognize ethical and professional responsibilities in engineering situations | B4: Identifies the ethical responsibilities and references at least one applicable professional code or standard (e.g., IEEE, NSPE, ISO). | C4: Describes relevant ethical responsibilities and refers generally to professional obligations or standards (without a specific citation). | D4: Acknowledges that an ethical issue exists but provides vague or incomplete responsibilities and no clear connection to professional standards. | E4: Fails to identify the ethical issue or misinterprets it. | F4: • Does the student clearly identify the ethical issue(s) in the scenario? | G4: Clearly identifies safety responsibilities: emergency stops, fail-safe procedures. Addresses misuse and cybersecurity: limiting physical access, considering unauthorized access. Explicitly refers to professional codes/standards: IEEE and NSPE. Mentions transparency and honesty: explaining decisions, assessments, and system limitations. Connects ethics back to the technical solution: how the drive-by-wire method maintains safety. | H4: 3 | I4: Explicitly addresses safety responsibilities: emergency stops, fail-safe procedures. Considers misuse and cybersecurity: restricted physical access, concern about unauthorized access to control systems. Refers directly to professional codes and standards (IEEE, NSPE) and links them to: transparency in conclusions and assessments, being open about limitations, integrating safety in the drive-by-wire method. | J4: 3 | K4: Explicitly cites IEEE and NSPE codes and standards and links them to behavior: academic integrity, professionalism. Emphasizes truth and transparency in findings and evaluations. Acknowledges need to be honest about limits and how safety is incorporated. Describes fail-safe procedures, emergency stop, and cybersecurity issues (unauthorized access) with restricted physical access to reduce misuse. | L4: 3 | M4: Clearly frames DBW as safety-critical, noting failures, unintended behavior, and liability as major ethical concerns. Explicitly cites IEEE and NSPE standards and connects them to integrity in testing and reporting. Puts safety above performance (emergency stop circuits, safe-state defaults, robust signal handling). Acknowledges hacking / misuse risks and mitigates via limited physical access and documentation. Adopts an explicit ethical stance focused on public protection and professional accountability → exemplary answer. | N4: 3 | P4: 3 | R4: 2 | T4: 2 | V4: 3 | X4: 1 | Z4: 2 | AB4: 3 | AD4: 2 | AF4: 2 | AH4: 3
F5: •Do they recognize their professional duties (e.g., safety, honesty, confidentiality, conflict of interest)?
F6: •Do they reference or appropriately relate to a professional code/standard (IEEE, NSPE, ISO, etc.)?
A8: PI42 Make informed judgments considering the impact of engineering solutions in global, societal, economic, and environmental contexts | B8: Demonstrates strong judgment and addresses all four factors (global, societal, economic, environmental) clearly and explicitly when considering the impact of engineering solutions. | C8: Capable of making informed judgments in considering the impact of engineering solutions, but misses at least one applicable factor among global, societal, economic, and environmental contexts. | D8: Demonstrates a basic ability to make informed judgments in considering the impact of engineering solutions, but misses two or more factors in the global, societal, economic, and environmental contexts. | E8: Lacks the ability to make informed judgments in considering the impact of engineering solutions, missing all four factors (global, societal, economic, and environmental contexts). | F8: •Does the student state a clear ethical decision or recommended action? | G8: Positive points: Recognizes need for thorough testing to prevent harm (safety / societal impact). Acknowledges software failure risks and the duty to be honest about limits → good ethical awareness. Mentions societal and environmental benefits (safer, more efficient, environmentally friendly EV system). Missing / weaker parts: Little to no explicit discussion of economic impact or global/cultural contexts. The impacts are stated in a general way, without concrete examples or trade-offs across the four dimensions. | H8: 2 | I8: Positive aspects: Strong ethical framing: obligation to make the system as safe as possible before deployment, including thorough testing in controlled situations. Identifies risk of software defects replacing mechanical links and the potential for harm. Emphasizes duty to be truthful and open about capabilities and constraints. Addresses societal and environmental impact: safer, more energy-efficient, climate-friendly system. What’s missing for the very top level: No explicit mention of economic considerations (cost, affordability, scalability, etc.). Global / cultural context is not clearly discussed (different regulations, user populations, regions, etc.). | J8: 2 | K8: Strong ethical framing: “primary goal is not to harm,” recognition that replacing mechanical links with software introduces risk of software bugs. Emphasizes extensive testing in controlled environments before real use → good safety judgment. Commits to honesty and transparency in reporting capabilities and limitations, with a concrete example (documenting unsupported failure modes and recommending not to operate). Notes positive societal impact (improved safety), environmental impact (climate-friendly, energy-efficient). However: Does not explicitly discuss economic aspects (cost, affordability, scalability) in this answer. Global/cultural context is not clearly articulated (regulations in different regions, different users, etc.). So he clearly makes informed ethical judgments and covers societal and environmental aspects well, but does not fully span all four contexts in this specific response | L8: 2 | M8: Shows safety judgment: choosing to keep mechanical steering/braking as fallback, explaining the trade-off between “advanced” full electronic control and risk in a student prototype. Explicitly balances cost, safety, and mission effectiveness in that decision. Discusses societal benefits: better safety, more efficient energy use. Mentions environmental impact: less impact due to energy-efficient control. Addresses economic impact: lower lifetime service costs by reducing mechanical components. References standards, rules, regulations, and the risk of unsafe deployments without them → clear ethical and professional judgment. Concludes with global framing: cleaner, more safety-conscious, accessible transportation aligned with global engineering needs. He explicitly touches all four contexts (global, societal, economic, environmental) plus ethics and trade-offs | N8: 3 | P8: 3 | R8: 3 | T8: 1 | V8: 3 | X8: 1 | Z8: 2 | AB8: 3 | AD8: 3 | AF8: 1 | AH8: 3
F9: • Is the final judgment consistent with professional integrity and protection of the public?
F10: • Does the student address each GEES factor (global, economic, environmental, societal), or clearly justify why any factor is not applicable?

Sheet SO2 Assessment Results
A1: SO2 Assessment Results
A2: *Add score 0-3 for each item
D3: Project Title | E3: PI21 Engineering Design | P3: PI22 Design Factors | S3: PI23 Constraints | V3: PI24 Standards | Y3: PIs Avg | Z3: Attainment | AA3: Comments: add comment on the team and individual student performance
A4: SN | B4: Student Name | C4: ID | E4: PI21 — Engineering Design Elements | M4: Group Avg | N4: Individual | O4: Avg | P4: Group | Q4: Individual | R4: Avg | S4: Group | T4: Individual | U4: Avg | V4: Group | W4: Individual | X4: Avg
E5: 1.1 | F5: 1.2 | G5: 1.3 | H5: 1.4 | I5: 1.5 | J5: 1.6 | K5: 1.7 | L5: 1.8
A6: 1 | B6: fsdfsa | C6: asdf | M6: =IF(COUNT(E6:L6)=0,"",AVERAGE(E6:L6)) | O6: =IF(COUNT(M6:N6)=0,"",AVERAGE(M6:N6)) | R6: =IF(COUNT(P6:Q6)=0,"",AVERAGE(P6:Q6)) | U6: =IF(COUNT(S6:T6)=0,"",AVERAGE(S6:T6)) | X6: =IF(COUNT(V6:W6)=0,"",AVERAGE(V6:W6)) | Y6: =IF(COUNT(M6:V6)=0,"",AVERAGE(M6:V6)) | Z6: =IF(Y6="","",IF(Y6<1,"BE",IF(Y6<2,"DE",IF(Y6<3,"ME","AE"))))
A7: 2 | M7: =IF(COUNT(E7:L7)=0,"",AVERAGE(E7:L7)) | O7: =IF(COUNT(M7:N7)=0,"",AVERAGE(M7:N7)) | R7: =IF(COUNT(P7:Q7)=0,"",AVERAGE(P7:Q7)) | U7: =IF(COUNT(S7:T7)=0,"",AVERAGE(S7:T7)) | X7: =IF(COUNT(V7:W7)=0,"",AVERAGE(V7:W7)) | Y7: =IF(COUNT(M7:V7)=0,"",AVERAGE(M7:V7)) | Z7: =IF(Y7="","",IF(Y7<1,"BE",IF(Y7<2,"DE",IF(Y7<3,"ME","AE"))))
A8: 3 | M8: =IF(COUNT(E8:L8)=0,"",AVERAGE(E8:L8)) | O8: =IF(COUNT(M8:N8)=0,"",AVERAGE(M8:N8)) | R8: =IF(COUNT(P8:Q8)=0,"",AVERAGE(P8:Q8)) | U8: =IF(COUNT(S8:T8)=0,"",AVERAGE(S8:T8)) | X8: =IF(COUNT(V8:W8)=0,"",AVERAGE(V8:W8)) | Y8: =IF(COUNT(M8:V8)=0,"",AVERAGE(M8:V8)) | Z8: =IF(Y8="","",IF(Y8<1,"BE",IF(Y8<2,"DE",IF(Y8<3,"ME","AE"))))
A9: 4 | M9: =IF(COUNT(E9:L9)=0,"",AVERAGE(E9:L9)) | O9: =IF(COUNT(M9:N9)=0,"",AVERAGE(M9:N9)) | R9: =IF(COUNT(P9:Q9)=0,"",AVERAGE(P9:Q9)) | U9: =IF(COUNT(S9:T9)=0,"",AVERAGE(S9:T9)) | X9: =IF(COUNT(V9:W9)=0,"",AVERAGE(V9:W9)) | Y9: =IF(COUNT(M9:V9)=0,"",AVERAGE(M9:V9)) | Z9: =IF(Y9="","",IF(Y9<1,"BE",IF(Y9<2,"DE",IF(Y9<3,"ME","AE"))))
A10: 5 | M10: =IF(COUNT(E10:L10)=0,"",AVERAGE(E10:L10)) | O10: =IF(COUNT(M10:N10)=0,"",AVERAGE(M10:N10)) | R10: =IF(COUNT(P10:Q10)=0,"",AVERAGE(P10:Q10)) | U10: =IF(COUNT(S10:T10)=0,"",AVERAGE(S10:T10)) | X10: =IF(COUNT(V10:W10)=0,"",AVERAGE(V10:W10)) | Y10: =IF(COUNT(M10:V10)=0,"",AVERAGE(M10:V10)) | Z10: =IF(Y10="","",IF(Y10<1,"BE",IF(Y10<2,"DE",IF(Y10<3,"ME","AE"))))
A11: 6 | M11: =IF(COUNT(E11:L11)=0,"",AVERAGE(E11:L11)) | O11: =IF(COUNT(M11:N11)=0,"",AVERAGE(M11:N11)) | R11: =IF(COUNT(P11:Q11)=0,"",AVERAGE(P11:Q11)) | U11: =IF(COUNT(S11:T11)=0,"",AVERAGE(S11:T11)) | X11: =IF(COUNT(V11:W11)=0,"",AVERAGE(V11:W11)) | Y11: =IF(COUNT(M11:V11)=0,"",AVERAGE(M11:V11)) | Z11: =IF(Y11="","",IF(Y11<1,"BE",IF(Y11<2,"DE",IF(Y11<3,"ME","AE"))))
A12: 7 | M12: =IF(COUNT(E12:L12)=0,"",AVERAGE(E12:L12)) | O12: =IF(COUNT(M12:N12)=0,"",AVERAGE(M12:N12)) | R12: =IF(COUNT(P12:Q12)=0,"",AVERAGE(P12:Q12)) | U12: =IF(COUNT(S12:T12)=0,"",AVERAGE(S12:T12)) | X12: =IF(COUNT(V12:W12)=0,"",AVERAGE(V12:W12)) | Y12: =IF(COUNT(M12:V12)=0,"",AVERAGE(M12:V12)) | Z12: =IF(Y12="","",IF(Y12<1,"BE",IF(Y12<2,"DE",IF(Y12<3,"ME","AE"))))
A13: 8 | M13: =IF(COUNT(E13:L13)=0,"",AVERAGE(E13:L13)) | O13: =IF(COUNT(M13:N13)=0,"",AVERAGE(M13:N13)) | R13: =IF(COUNT(P13:Q13)=0,"",AVERAGE(P13:Q13)) | U13: =IF(COUNT(S13:T13)=0,"",AVERAGE(S13:T13)) | X13: =IF(COUNT(V13:W13)=0,"",AVERAGE(V13:W13)) | Y13: =IF(COUNT(M13:V13)=0,"",AVERAGE(M13:V13)) | Z13: =IF(Y13="","",IF(Y13<1,"BE",IF(Y13<2,"DE",IF(Y13<3,"ME","AE"))))
A14: 9 | M14: =IF(COUNT(E14:L14)=0,"",AVERAGE(E14:L14)) | O14: =IF(COUNT(M14:N14)=0,"",AVERAGE(M14:N14)) | R14: =IF(COUNT(P14:Q14)=0,"",AVERAGE(P14:Q14)) | U14: =IF(COUNT(S14:T14)=0,"",AVERAGE(S14:T14)) | X14: =IF(COUNT(V14:W14)=0,"",AVERAGE(V14:W14)) | Y14: =IF(COUNT(M14:V14)=0,"",AVERAGE(M14:V14)) | Z14: =IF(Y14="","",IF(Y14<1,"BE",IF(Y14<2,"DE",IF(Y14<3,"ME","AE"))))
A15: 10 | M15: =IF(COUNT(E15:L15)=0,"",AVERAGE(E15:L15)) | O15: =IF(COUNT(M15:N15)=0,"",AVERAGE(M15:N15)) | R15: =IF(COUNT(P15:Q15)=0,"",AVERAGE(P15:Q15)) | U15: =IF(COUNT(S15:T15)=0,"",AVERAGE(S15:T15)) | X15: =IF(COUNT(V15:W15)=0,"",AVERAGE(V15:W15)) | Y15: =IF(COUNT(M15:V15)=0,"",AVERAGE(M15:V15)) | Z15: =IF(Y15="","",IF(Y15<1,"BE",IF(Y15<2,"DE",IF(Y15<3,"ME","AE"))))
A16: 11 | M16: =IF(COUNT(E16:L16)=0,"",AVERAGE(E16:L16)) | O16: =IF(COUNT(M16:N16)=0,"",AVERAGE(M16:N16)) | R16: =IF(COUNT(P16:Q16)=0,"",AVERAGE(P16:Q16)) | U16: =IF(COUNT(S16:T16)=0,"",AVERAGE(S16:T16)) | X16: =IF(COUNT(V16:W16)=0,"",AVERAGE(V16:W16)) | Y16: =IF(COUNT(M16:V16)=0,"",AVERAGE(M16:V16)) | Z16: =IF(Y16="","",IF(Y16<1,"BE",IF(Y16<2,"DE",IF(Y16<3,"ME","AE"))))
A17: 12 | M17: =IF(COUNT(E17:L17)=0,"",AVERAGE(E17:L17)) | O17: =IF(COUNT(M17:N17)=0,"",AVERAGE(M17:N17)) | R17: =IF(COUNT(P17:Q17)=0,"",AVERAGE(P17:Q17)) | U17: =IF(COUNT(S17:T17)=0,"",AVERAGE(S17:T17)) | X17: =IF(COUNT(V17:W17)=0,"",AVERAGE(V17:W17)) | Y17: =IF(COUNT(M17:V17)=0,"",AVERAGE(M17:V17)) | Z17: =IF(Y17="","",IF(Y17<1,"BE",IF(Y17<2,"DE",IF(Y17<3,"ME","AE"))))
A18: 13 | M18: =IF(COUNT(E18:L18)=0,"",AVERAGE(E18:L18)) | O18: =IF(COUNT(M18:N18)=0,"",AVERAGE(M18:N18)) | R18: =IF(COUNT(P18:Q18)=0,"",AVERAGE(P18:Q18)) | U18: =IF(COUNT(S18:T18)=0,"",AVERAGE(S18:T18)) | X18: =IF(COUNT(V18:W18)=0,"",AVERAGE(V18:W18)) | Y18: =IF(COUNT(M18:V18)=0,"",AVERAGE(M18:V18)) | Z18: =IF(Y18="","",IF(Y18<1,"BE",IF(Y18<2,"DE",IF(Y18<3,"ME","AE"))))
A19: 14 | M19: =IF(COUNT(E19:L19)=0,"",AVERAGE(E19:L19)) | O19: =IF(COUNT(M19:N19)=0,"",AVERAGE(M19:N19)) | R19: =IF(COUNT(P19:Q19)=0,"",AVERAGE(P19:Q19)) | U19: =IF(COUNT(S19:T19)=0,"",AVERAGE(S19:T19)) | X19: =IF(COUNT(V19:W19)=0,"",AVERAGE(V19:W19)) | Y19: =IF(COUNT(M19:V19)=0,"",AVERAGE(M19:V19)) | Z19: =IF(Y19="","",IF(Y19<1,"BE",IF(Y19<2,"DE",IF(Y19<3,"ME","AE"))))
K20: Class PI % | O20: =IFERROR(TEXT(COUNTIF(O6:O19,">=2")/COUNT(O6:O19),"0%"),"") | R20: =IFERROR(TEXT(COUNTIF(R6:R19,">=2")/COUNT(R6:R19),"0%"),"") | U20: =IFERROR(TEXT(COUNTIF(U6:U19,">=2")/COUNT(U6:U19),"0%"),"") | X20: =IFERROR(TEXT(COUNTIF(X6:X19,">=2")/COUNT(X6:X19),"0%"),"") | Y20: SO Result | Z20: =IFERROR(TEXT((COUNTIF(Z6:Z19,"AE")+COUNTIF(Z6:Z19,"ME"))/(COUNTIF(Z6:Z19,"AE")+COUNTIF(Z6:Z19,"ME")+COUNTIF(Z6:Z19,"DE")+COUNTIF(Z6:Z19,"BE")),"0%"),"")
A21: Notes: -PI results are calculated as the percentage of students who achieved a score of 2 or higher. -The SO result is calculated as the percentage of students whose average PI score is 2.0 or higher. -Group assessment is based on group work, such as a project report, demonstration, presentation, etc. -Individual assessment is based on each student’s individual performance, such as an oral discussion, individual reflection, exam question, etc.

Sheet SO4 Assessment Results
C1: Evluation Type | D1: IE | E1: IE
A2: No | B2: ID | C2: Name | D2: PI41 | E2: PI42 | F2: Average | G2: Achievement
D3: 1 | E3: 1 | I3: IE | J3: Individual evaluation
A4: 1 | B4: =IF(#REF!="","",#REF!) -> #REF! | C4: =IF(#REF!="","",#REF!) -> #REF! | D4: {=IF(#REF!="","", INDEX('SO4 Rubric'!$H$4:$ZZ$4, 1, (ROW()-4)*2+1))} -> #REF! | E4: {=IF(#REF!="","", INDEX('SO4 Rubric'!$H$8:$ZZ$8, 1, (ROW()-4)*2+1))} -> #REF! | F4: =IF(SUMPRODUCT(--(D4:E4<>""))=0,"",ROUND(SUMPRODUCT($D$3:$E$3,D4:E4)/COUNTIF($D$3:$E$3,1),0)) -> #REF! | G4: =IF(F4=""," ",VLOOKUP(F4,'Lookup Tables'!$D$9:$E$12,2)) -> #REF!
A5: 2 | B5: =IF(#REF!="","",#REF!) -> #REF! | C5: =IF(#REF!="","",#REF!) -> #REF! | D5: {=IF(#REF!="","", INDEX('SO4 Rubric'!$H$4:$ZZ$4, 1, (ROW()-4)*2+1))} -> #REF! | E5: {=IF(#REF!="","", INDEX('SO4 Rubric'!$H$8:$ZZ$8, 1, (ROW()-4)*2+1))} -> #REF! | F5: =IF(SUMPRODUCT(--(D5:E5<>""))=0,"",ROUND(SUMPRODUCT($D$3:$E$3,D5:E5)/COUNTIF($D$3:$E$3,1),0)) -> #REF! | G5: =IF(F5=""," ",VLOOKUP(F5,'Lookup Tables'!$D$9:$E$12,2)) -> #REF!
A6: 3 | B6: =IF(#REF!="","",#REF!) -> #REF! | C6: =IF(#REF!="","",#REF!) -> #REF! | D6: {=IF(#REF!="","", INDEX('SO4 Rubric'!$H$4:$ZZ$4, 1, (ROW()-4)*2+1))} -> #REF! | E6: {=IF(#REF!="","", INDEX('SO4 Rubric'!$H$8:$ZZ$8, 1, (ROW()-4)*2+1))} -> #REF! | F6: =IF(SUMPRODUCT(--(D6:E6<>""))=0,"",ROUND(SUMPRODUCT($D$3:$E$3,D6:E6)/COUNTIF($D$3:$E$3,1),0)) -> #REF! | G6: =IF(F6=""," ",VLOOKUP(F6,'Lookup Tables'!$D$9:$E$12,2)) -> #REF!
A7: 4 | B7: =IF(#REF!="","",#REF!) -> #REF! | C7: =IF(#REF!="","",#REF!) -> #REF! | D7: {=IF(#REF!="","", INDEX('SO4 Rubric'!$H$4:$ZZ$4, 1, (ROW()-4)*2+1))} -> #REF! | E7: {=IF(#REF!="","", INDEX('SO4 Rubric'!$H$8:$ZZ$8, 1, (ROW()-4)*2+1))} -> #REF! | F7: =IF(SUMPRODUCT(--(D7:E7<>""))=0,"",ROUND(SUMPRODUCT($D$3:$E$3,D7:E7)/COUNTIF($D$3:$E$3,1),0)) -> #REF! | G7: =IF(F7=""," ",VLOOKUP(F7,'Lookup Tables'!$D$9:$E$12,2)) -> #REF!
A8: 5 | B8: =IF(#REF!="","",#REF!) -> #REF! | C8: =IF(#REF!="","",#REF!) -> #REF! | D8: {=IF(#REF!="","", INDEX('SO4 Rubric'!$H$4:$ZZ$4, 1, (ROW()-4)*2+1))} -> #REF! | E8: {=IF(#REF!="","", INDEX('SO4 Rubric'!$H$8:$ZZ$8, 1, (ROW()-4)*2+1))} -> #REF! | F8: =IF(SUMPRODUCT(--(D8:E8<>""))=0,"",ROUND(SUMPRODUCT($D$3:$E$3,D8:E8)/COUNTIF($D$3:$E$3,1),0)) -> #REF! | G8: =IF(F8=""," ",VLOOKUP(F8,'Lookup Tables'!$D$9:$E$12,2)) -> #REF!
A9: 6 | B9: =IF(#REF!="","",#REF!) -> #REF! | C9: =IF(#REF!="","",#REF!) -> #REF! | D9: {=IF(#REF!="","", INDEX('SO4 Rubric'!$H$4:$ZZ$4, 1, (ROW()-4)*2+1))} -> #REF! | E9: {=IF(#REF!="","", INDEX('SO4 Rubric'!$H$8:$ZZ$8, 1, (ROW()-4)*2+1))} -> #REF! | F9: =IF(SUMPRODUCT(--(D9:E9<>""))=0,"",ROUND(SUMPRODUCT($D$3:$E$3,D9:E9)/COUNTIF($D$3:$E$3,1),0)) -> #REF! | G9: =IF(F9=""," ",VLOOKUP(F9,'Lookup Tables'!$D$9:$E$12,2)) -> #REF!
A10: 7 | B10: =IF(#REF!="","",#REF!) -> #REF! | C10: =IF(#REF!="","",#REF!) -> #REF! | D10: {=IF(#REF!="","", INDEX('SO4 Rubric'!$H$4:$ZZ$4, 1, (ROW()-4)*2+1))} -> #REF! | E10: {=IF(#REF!="","", INDEX('SO4 Rubric'!$H$8:$ZZ$8, 1, (ROW()-4)*2+1))} -> #REF! | F10: =IF(SUMPRODUCT(--(D10:E10<>""))=0,"",ROUND(SUMPRODUCT($D$3:$E$3,D10:E10)/COUNTIF($D$3:$E$3,1),0)) -> #REF! | G10: =IF(F10=""," ",VLOOKUP(F10,'Lookup Tables'!$D$9:$E$12,2)) -> #REF!
A11: 8 | B11: =IF(#REF!="","",#REF!) -> #REF! | C11: =IF(#REF!="","",#REF!) -> #REF! | D11: {=IF(#REF!="","", INDEX('SO4 Rubric'!$H$4:$ZZ$4, 1, (ROW()-4)*2+1))} -> #REF! | E11: {=IF(#REF!="","", INDEX('SO4 Rubric'!$H$8:$ZZ$8, 1, (ROW()-4)*2+1))} -> #REF! | F11: =IF(SUMPRODUCT(--(D11:E11<>""))=0,"",ROUND(SUMPRODUCT($D$3:$E$3,D11:E11)/COUNTIF($D$3:$E$3,1),0)) -> #REF! | G11: =IF(F11=""," ",VLOOKUP(F11,'Lookup Tables'!$D$9:$E$12,2)) -> #REF! | H11: =IF(ISBLANK(#REF!),"",IFERROR(ROUND(3*(#REF!/#REF!),0),"")) | I11: =IF(ISBLANK(#REF!),"",IFERROR(ROUND(3*(#REF!/#REF!),0),"")) | J11: =IF(ISBLANK(#REF!),"",IFERROR(ROUND(3*(#REF!/#REF!),0),"")) | K11: =IF(ISBLANK(#REF!),"",IFERROR(ROUND(3*(#REF!/#REF!),0),"")) | L11: =IF(SUMPRODUCT(--(H11:K11<>""))=0,"",SUMPRODUCT(#REF!,H11:K11)/COUNTIF(#REF!,1)) | M11: =IF(L11="","",L11/3)
A12: 9 | B12: =IF(#REF!="","",#REF!) -> #REF! | C12: =IF(#REF!="","",#REF!) -> #REF! | D12: {=IF(#REF!="","", INDEX('SO4 Rubric'!$H$4:$ZZ$4, 1, (ROW()-4)*2+1))} -> #REF! | E12: {=IF(#REF!="","", INDEX('SO4 Rubric'!$H$8:$ZZ$8, 1, (ROW()-4)*2+1))} -> #REF! | F12: =IF(SUMPRODUCT(--(D12:E12<>""))=0,"",ROUND(SUMPRODUCT($D$3:$E$3,D12:E12)/COUNTIF($D$3:$E$3,1),0)) -> #REF! | G12: =IF(F12=""," ",VLOOKUP(F12,'Lookup Tables'!$D$9:$E$12,2)) -> #REF! | H12: =IF(ISBLANK(#REF!),"",IFERROR(ROUND(3*(#REF!/#REF!),0),"")) | I12: =IF(ISBLANK(#REF!),"",IFERROR(ROUND(3*(#REF!/#REF!),0),"")) | J12: =IF(ISBLANK(#REF!),"",IFERROR(ROUND(3*(#REF!/#REF!),0),"")) | K12: =IF(ISBLANK(#REF!),"",IFERROR(ROUND(3*(#REF!/#REF!),0),"")) | L12: =IF(SUMPRODUCT(--(H12:K12<>""))=0,"",SUMPRODUCT(#REF!,H12:K12)/COUNTIF(#REF!,1)) | M12: =IF(L12="","",L12/3)
A13: 10 | B13: =IF(#REF!="","",#REF!) -> #REF! | C13: =IF(#REF!="","",#REF!) -> #REF! | D13: {=IF(#REF!="","", INDEX('SO4 Rubric'!$H$4:$ZZ$4, 1, (ROW()-4)*2+1))} -> #REF! | E13: {=IF(#REF!="","", INDEX('SO4 Rubric'!$H$8:$ZZ$8, 1, (ROW()-4)*2+1))} -> #REF! | F13: =IF(SUMPRODUCT(--(D13:E13<>""))=0,"",ROUND(SUMPRODUCT($D$3:$E$3,D13:E13)/COUNTIF($D$3:$E$3,1),0)) -> #REF! | G13: =IF(F13=""," ",VLOOKUP(F13,'Lookup Tables'!$D$9:$E$12,2)) -> #REF! | H13: =IF(ISBLANK(#REF!),"",IFERROR(ROUND(3*(#REF!/#REF!),0),"")) | I13: =IF(ISBLANK(#REF!),"",IFERROR(ROUND(3*(#REF!/#REF!),0),"")) | J13: =IF(ISBLANK(#REF!),"",IFERROR(ROUND(3*(#REF!/#REF!),0),"")) | K13: =IF(ISBLANK(#REF!),"",IFERROR(ROUND(3*(#REF!/#REF!),0),"")) | L13: =IF(SUMPRODUCT(--(H13:K13<>""))=0,"",SUMPRODUCT(#REF!,H13:K13)/COUNTIF(#REF!,1)) | M13: =IF(L13="","",L13/3)
A14: 11 | B14: =IF(#REF!="","",#REF!) -> #REF! | C14: =IF(#REF!="","",#REF!) -> #REF! | D14: {=IF(#REF!="","", INDEX('SO4 Rubric'!$H$4:$ZZ$4, 1, (ROW()-4)*2+1))} -> #REF! | E14: {=IF(#REF!="","", INDEX('SO4 Rubric'!$H$8:$ZZ$8, 1, (ROW()-4)*2+1))} -> #REF! | F14: =IF(SUMPRODUCT(--(D14:E14<>""))=0,"",ROUND(SUMPRODUCT($D$3:$E$3,D14:E14)/COUNTIF($D$3:$E$3,1),0)) -> #REF! | G14: =IF(F14=""," ",VLOOKUP(F14,'Lookup Tables'!$D$9:$E$12,2)) -> #REF! | H14: =IF(ISBLANK(#REF!),"",IFERROR(ROUND(3*(#REF!/#REF!),0),"")) | I14: =IF(ISBLANK(#REF!),"",IFERROR(ROUND(3*(#REF!/#REF!),0),"")) | J14: =IF(ISBLANK(#REF!),"",IFERROR(ROUND(3*(#REF!/#REF!),0),"")) | K14: =IF(ISBLANK(#REF!),"",IFERROR(ROUND(3*(#REF!/#REF!),0),"")) | L14: =IF(SUMPRODUCT(--(H14:K14<>""))=0,"",SUMPRODUCT(#REF!,H14:K14)/COUNTIF(#REF!,1)) | M14: =IF(L14="","",L14/3)
A15: 12 | B15: =IF(#REF!="","",#REF!) -> #REF! | C15: =IF(#REF!="","",#REF!) -> #REF! | D15: {=IF(#REF!="","", INDEX('SO4 Rubric'!$H$4:$ZZ$4, 1, (ROW()-4)*2+1))} -> #REF! | E15: {=IF(#REF!="","", INDEX('SO4 Rubric'!$H$8:$ZZ$8, 1, (ROW()-4)*2+1))} -> #REF! | F15: =IF(SUMPRODUCT(--(D15:E15<>""))=0,"",ROUND(SUMPRODUCT($D$3:$E$3,D15:E15)/COUNTIF($D$3:$E$3,1),0)) -> #REF! | G15: =IF(F15=""," ",VLOOKUP(F15,'Lookup Tables'!$D$9:$E$12,2)) -> #REF! | H15: =IF(ISBLANK(#REF!),"",IFERROR(ROUND(3*(#REF!/#REF!),0),"")) | I15: =IF(ISBLANK(#REF!),"",IFERROR(ROUND(3*(#REF!/#REF!),0),"")) | J15: =IF(ISBLANK(#REF!),"",IFERROR(ROUND(3*(#REF!/#REF!),0),"")) | K15: =IF(ISBLANK(#REF!),"",IFERROR(ROUND(3*(#REF!/#REF!),0),"")) | L15: =IF(SUMPRODUCT(--(H15:K15<>""))=0,"",SUMPRODUCT(#REF!,H15:K15)/COUNTIF(#REF!,1)) | M15: =IF(L15="","",L15/3)
A16: 13 | B16: =IF(#REF!="","",#REF!) -> #REF! | C16: =IF(#REF!="","",#REF!) -> #REF! | D16: {=IF(#REF!="","", INDEX('SO4 Rubric'!$H$4:$ZZ$4, 1, (ROW()-4)*2+1))} -> #REF! | E16: {=IF(#REF!="","", INDEX('SO4 Rubric'!$H$8:$ZZ$8, 1, (ROW()-4)*2+1))} -> #REF! | F16: =IF(SUMPRODUCT(--(D16:E16<>""))=0,"",ROUND(SUMPRODUCT($D$3:$E$3,D16:E16)/COUNTIF($D$3:$E$3,1),0)) -> #REF! | G16: =IF(F16=""," ",VLOOKUP(F16,'Lookup Tables'!$D$9:$E$12,2)) -> #REF! | H16: =IF(ISBLANK(#REF!),"",IFERROR(ROUND(3*(#REF!/#REF!),0),"")) | I16: =IF(ISBLANK(#REF!),"",IFERROR(ROUND(3*(#REF!/#REF!),0),"")) | J16: =IF(ISBLANK(#REF!),"",IFERROR(ROUND(3*(#REF!/#REF!),0),"")) | K16: =IF(ISBLANK(#REF!),"",IFERROR(ROUND(3*(#REF!/#REF!),0),"")) | L16: =IF(SUMPRODUCT(--(H16:K16<>""))=0,"",SUMPRODUCT(#REF!,H16:K16)/COUNTIF(#REF!,1)) | M16: =IF(L16="","",L16/3)
A17: 14 | B17: =IF(#REF!="","",#REF!) -> #REF! | C17: =IF(#REF!="","",#REF!) -> #REF! | D17: {=IF(#REF!="","", INDEX('SO4 Rubric'!$H$4:$ZZ$4, 1, (ROW()-4)*2+1))} -> #REF! | E17: {=IF(#REF!="","", INDEX('SO4 Rubric'!$H$8:$ZZ$8, 1, (ROW()-4)*2+1))} -> #REF! | F17: =IF(SUMPRODUCT(--(D17:E17<>""))=0,"",ROUND(SUMPRODUCT($D$3:$E$3,D17:E17)/COUNTIF($D$3:$E$3,1),0)) -> #REF! | G17: =IF(F17=""," ",VLOOKUP(F17,'Lookup Tables'!$D$9:$E$12,2)) -> #REF! | H17: =IF(ISBLANK(#REF!),"",IFERROR(ROUND(3*(#REF!/#REF!),0),"")) | I17: =IF(ISBLANK(#REF!),"",IFERROR(ROUND(3*(#REF!/#REF!),0),"")) | J17: =IF(ISBLANK(#REF!),"",IFERROR(ROUND(3*(#REF!/#REF!),0),"")) | K17: =IF(ISBLANK(#REF!),"",IFERROR(ROUND(3*(#REF!/#REF!),0),"")) | L17: =IF(SUMPRODUCT(--(H17:K17<>""))=0,"",SUMPRODUCT(#REF!,H17:K17)/COUNTIF(#REF!,1)) | M17: =IF(L17="","",L17/3)
A18: 15 | B18: =IF(#REF!="","",#REF!) -> #REF! | C18: =IF(#REF!="","",#REF!) -> #REF! | D18: {=IF(#REF!="","", INDEX('SO4 Rubric'!$H$4:$ZZ$4, 1, (ROW()-4)*2+1))} -> #REF! | E18: {=IF(#REF!="","", INDEX('SO4 Rubric'!$H$8:$ZZ$8, 1, (ROW()-4)*2+1))} -> #REF! | F18: =IF(SUMPRODUCT(--(D18:E18<>""))=0,"",ROUND(SUMPRODUCT($D$3:$E$3,D18:E18)/COUNTIF($D$3:$E$3,1),0)) -> #REF! | G18: =IF(F18=""," ",VLOOKUP(F18,'Lookup Tables'!$D$9:$E$12,2)) -> #REF! | H18: =IF(ISBLANK(#REF!),"",IFERROR(ROUND(3*(#REF!/#REF!),0),"")) | I18: =IF(ISBLANK(#REF!),"",IFERROR(ROUND(3*(#REF!/#REF!),0),"")) | J18: =IF(ISBLANK(#REF!),"",IFERROR(ROUND(3*(#REF!/#REF!),0),"")) | K18: =IF(ISBLANK(#REF!),"",IFERROR(ROUND(3*(#REF!/#REF!),0),"")) | L18: =IF(SUMPRODUCT(--(H18:K18<>""))=0,"",SUMPRODUCT(#REF!,H18:K18)/COUNTIF(#REF!,1)) | M18: =IF(L18="","",L18/3)
A19: 16 | B19: =IF(#REF!="","",#REF!) -> #REF! | C19: =IF(#REF!="","",#REF!) -> #REF! | D19: {=IF(#REF!="","", INDEX('SO4 Rubric'!$H$4:$ZZ$4, 1, (ROW()-4)*2+1))} -> #REF! | E19: {=IF(#REF!="","", INDEX('SO4 Rubric'!$H$8:$ZZ$8, 1, (ROW()-4)*2+1))} -> #REF! | F19: =IF(SUMPRODUCT(--(D19:E19<>""))=0,"",ROUND(SUMPRODUCT($D$3:$E$3,D19:E19)/COUNTIF($D$3:$E$3,1),0)) -> #REF! | G19: =IF(F19=""," ",VLOOKUP(F19,'Lookup Tables'!$D$9:$E$12,2)) -> #REF! | H19: =IF(ISBLANK(#REF!),"",IFERROR(ROUND(3*(#REF!/#REF!),0),"")) | I19: =IF(ISBLANK(#REF!),"",IFERROR(ROUND(3*(#REF!/#REF!),0),"")) | J19: =IF(ISBLANK(#REF!),"",IFERROR(ROUND(3*(#REF!/#REF!),0),"")) | K19: =IF(ISBLANK(#REF!),"",IFERROR(ROUND(3*(#REF!/#REF!),0),"")) | L19: =IF(SUMPRODUCT(--(H19:K19<>""))=0,"",SUMPRODUCT(#REF!,H19:K19)/COUNTIF(#REF!,1)) | M19: =IF(L19="","",L19/3)
A20: 17 | B20: =IF(#REF!="","",#REF!) -> #REF! | C20: =IF(#REF!="","",#REF!) -> #REF! | D20: {=IF(#REF!="","", INDEX('SO4 Rubric'!$H$4:$ZZ$4, 1, (ROW()-4)*2+1))} -> #REF! | E20: {=IF(#REF!="","", INDEX('SO4 Rubric'!$H$8:$ZZ$8, 1, (ROW()-4)*2+1))} -> #REF! | F20: =IF(SUMPRODUCT(--(D20:E20<>""))=0,"",ROUND(SUMPRODUCT($D$3:$E$3,D20:E20)/COUNTIF($D$3:$E$3,1),0)) -> #REF! | G20: =IF(F20=""," ",VLOOKUP(F20,'Lookup Tables'!$D$9:$E$12,2)) -> #REF! | H20: =IF(ISBLANK(#REF!),"",IFERROR(ROUND(3*(#REF!/#REF!),0),"")) | I20: =IF(ISBLANK(#REF!),"",IFERROR(ROUND(3*(#REF!/#REF!),0),"")) | J20: =IF(ISBLANK(#REF!),"",IFERROR(ROUND(3*(#REF!/#REF!),0),"")) | K20: =IF(ISBLANK(#REF!),"",IFERROR(ROUND(3*(#REF!/#REF!),0),"")) | L20: =IF(SUMPRODUCT(--(H20:K20<>""))=0,"",SUMPRODUCT(#REF!,H20:K20)/COUNTIF(#REF!,1)) | M20: =IF(L20="","",L20/3)
A21: 18 | B21: =IF(#REF!="","",#REF!) -> #REF! | C21: =IF(#REF!="","",#REF!) -> #REF! | D21: {=IF(#REF!="","", INDEX('SO4 Rubric'!$H$4:$ZZ$4, 1, (ROW()-4)*2+1))} -> #REF! | E21: {=IF(#REF!="","", INDEX('SO4 Rubric'!$H$8:$ZZ$8, 1, (ROW()-4)*2+1))} -> #REF! | F21: =IF(SUMPRODUCT(--(D21:E21<>""))=0,"",ROUND(SUMPRODUCT($D$3:$E$3,D21:E21)/COUNTIF($D$3:$E$3,1),0)) -> #REF! | G21: =IF(F21=""," ",VLOOKUP(F21,'Lookup Tables'!$D$9:$E$12,2)) -> #REF! | H21: =IF(ISBLANK(#REF!),"",IFERROR(ROUND(3*(#REF!/#REF!),0),"")) | I21: =IF(ISBLANK(#REF!),"",IFERROR(ROUND(3*(#REF!/#REF!),0),"")) | J21: =IF(ISBLANK(#REF!),"",IFERROR(ROUND(3*(#REF!/#REF!),0),"")) | K21: =IF(ISBLANK(#REF!),"",IFERROR(ROUND(3*(#REF!/#REF!),0),"")) | L21: =IF(SUMPRODUCT(--(H21:K21<>""))=0,"",SUMPRODUCT(#REF!,H21:K21)/COUNTIF(#REF!,1)) | M21: =IF(L21="","",L21/3)
A22: 19 | B22: =IF(#REF!="","",#REF!) -> #REF! | C22: =IF(#REF!="","",#REF!) -> #REF! | D22: {=IF(#REF!="","", INDEX('SO4 Rubric'!$H$4:$ZZ$4, 1, (ROW()-4)*2+1))} -> #REF! | E22: {=IF(#REF!="","", INDEX('SO4 Rubric'!$H$8:$ZZ$8, 1, (ROW()-4)*2+1))} -> #REF! | F22: =IF(SUMPRODUCT(--(D22:E22<>""))=0,"",ROUND(SUMPRODUCT($D$3:$E$3,D22:E22)/COUNTIF($D$3:$E$3,1),0)) -> #REF! | G22: =IF(F22=""," ",VLOOKUP(F22,'Lookup Tables'!$D$9:$E$12,2)) -> #REF! | H22: =IF(ISBLANK(#REF!),"",IFERROR(ROUND(3*(#REF!/#REF!),0),"")) | I22: =IF(ISBLANK(#REF!),"",IFERROR(ROUND(3*(#REF!/#REF!),0),"")) | J22: =IF(ISBLANK(#REF!),"",IFERROR(ROUND(3*(#REF!/#REF!),0),"")) | K22: =IF(ISBLANK(#REF!),"",IFERROR(ROUND(3*(#REF!/#REF!),0),"")) | L22: =IF(SUMPRODUCT(--(H22:K22<>""))=0,"",SUMPRODUCT(#REF!,H22:K22)/COUNTIF(#REF!,1)) | M22: =IF(L22="","",L22/3)
A23: 20 | B23: =IF(#REF!="","",#REF!) -> #REF! | C23: =IF(#REF!="","",#REF!) -> #REF! | D23: {=IF(#REF!="","", INDEX('SO4 Rubric'!$H$4:$ZZ$4, 1, (ROW()-4)*2+1))} -> #REF! | E23: {=IF(#REF!="","", INDEX('SO4 Rubric'!$H$8:$ZZ$8, 1, (ROW()-4)*2+1))} -> #REF! | F23: =IF(SUMPRODUCT(--(D23:E23<>""))=0,"",ROUND(SUMPRODUCT($D$3:$E$3,D23:E23)/COUNTIF($D$3:$E$3,1),0)) -> #REF! | G23: =IF(F23=""," ",VLOOKUP(F23,'Lookup Tables'!$D$9:$E$12,2)) -> #REF! | H23: =IF(ISBLANK(#REF!),"",IFERROR(ROUND(3*(#REF!/#REF!),0),"")) | I23: =IF(ISBLANK(#REF!),"",IFERROR(ROUND(3*(#REF!/#REF!),0),"")) | J23: =IF(ISBLANK(#REF!),"",IFERROR(ROUND(3*(#REF!/#REF!),0),"")) | K23: =IF(ISBLANK(#REF!),"",IFERROR(ROUND(3*(#REF!/#REF!),0),"")) | L23: =IF(SUMPRODUCT(--(H23:K23<>""))=0,"",SUMPRODUCT(#REF!,H23:K23)/COUNTIF(#REF!,1)) | M23: =IF(L23="","",L23/3)
D24: PI Results | F24: SO Result | G24: BE | H24: =COUNTIF('SO4 Assessment Results'!$G$4:$G$23,G24) -> 0 | I24: =IFERROR(TEXT(((H26+H27)/SUM(H24:H27)),"0%"),"")
D25: PI41 | E25: PI42 | G25: DE | H25: =COUNTIF('SO4 Assessment Results'!$G$4:$G$23,G25) -> 0
D26: =IFERROR(AVERAGE(D4:D20),"") | E26: =IFERROR(AVERAGE(E4:E20),"") | G26: ME | H26: =COUNTIF('SO4 Assessment Results'!$G$4:$G$23,G26) -> 0 | K26: =IFERROR(AVERAGE(K11:K23),"")
D27: =IFERROR(TEXT((COUNTIF(D4:D23,2) + COUNTIF(D4:D23,3)) / COUNT(D4:D23),"0%"),"") | E27: =IFERROR(TEXT((COUNTIF(E4:E23,2) + COUNTIF(E4:E23,3)) / COUNT(E4:E23),"0%"),"") | G27: AE | H27: =COUNTIF('SO4 Assessment Results'!$G$4:$G$23,G27) -> 0
B30: Comment on the PIs results if any is below 2 or if the SO is below 70%
B31: All PIs and the SO results are above the threshold

Sheet Student work Description
A1: Student Work Description
A3: SO - PI | B3: Assessment Item | D3: Questions Used | N3: Justification of assessment item selection
A4: =#REF! -> #REF! | B4: =IF(#REF!=0,"",#REF! & " - " &#REF!) -> #REF!
A5: =#REF! -> #REF! | B5: =IF(#REF!=0,"",#REF! & " - " &#REF!) -> #REF!
A6: =#REF! -> #REF! | B6: =IF(#REF!=0,"",#REF! & " - " &#REF!) -> #REF!
A7: =#REF! -> #REF! | B7: =IF(#REF!=0,"",#REF! & " - " &#REF!) -> #REF!
A8: =#REF! -> #REF! | B8: =IF(#REF!=0,"",#REF! & " - " &#REF!) -> #REF!
A9: =#REF! -> #REF! | B9: =IF(#REF!=0,"",#REF! & " - " &#REF!) -> #REF!
A10: =#REF! -> #REF! | B10: =IF(#REF!=0,"",#REF! & " - " &#REF!) -> #REF!
A11: =#REF! -> #REF! | B11: =IF(#REF!=0,"",#REF! & " - " &#REF!) -> #REF!
A12: =#REF! -> #REF! | B12: =IF(#REF!=0,"",#REF! & " - " &#REF!) -> #REF!
A13: =#REF! -> #REF! | B13: =IF(#REF!=0,"",#REF! & " - " &#REF!) -> #REF!
A14: =#REF! -> #REF! | B14: =IF(#REF!=0,"",#REF! & " - " &#REF!) -> #REF!
A15: =#REF! -> #REF! | B15: =IF(#REF!=0,"",#REF! & " - " &#REF!) -> #REF!

Sheet SO4
B3: Key Performance Indicators and Rubrics for Student Outcome:
B4: 4. Recognize professional responsibilities and make informed judgments in computing practice based on legal and ethical principles.
B5: KPI Nbr. | C5: KPI Definition | D5: Level 0: Below Expectation (BE) | E5: Level 1: Developing Expectation (DE) | F5: Level 2: Meet Expectation (ME) | G5: Level 3: Above Expectation (AE)
B6: 4.1 | C6: Demonstrate ability to recognize impact and determine best practices. | D6: Little recognition of the impact of computing practices on individuals, organizations and society. | E6: Some recognition of the effects of computing practices on individuals, organizations and society, but little demonstrated ability to determine best practices. | F6: Recognizes some effects of computing practices onindividuals, organizations and society, and demonstrates acceptable ability to determine best practices | G6: Recognizes the effects of computing practices on individuals, organization, and society and demonstrates good ability to determine good practices
B7: 4.2 | C7: Demonstrates an ability to recognize ethical dilemmas and apply professional ethical practices to make appropriate decisions | D7: Needs assistance to identify ethical dilemmas and to apply the code of ethics from professional societies and/or ethical theories | E7: Demonstrates some ability to identify ethical dilemmas and is aware of, but cannot necessarily apply, a professional code of ethics and/or ethical theory | F7: Demonstrates acceptable ability to identify ethical dilemmas and recognizes basic elements of a professional code of ethics and/or ethical theory | G7: Can apply elements from a professional code of ethics and/or ethical theory to recognize ethical dilemmas and analyze them.

Sheet SO5
B3: Key Performance Indicators and Rubrics for Student Outcome:
B4: 5. Function effectively as a member or leader of a team engaged in activities appropriate to the program’s discipline.
B5: KPI Nbr. | C5: KPI Definition | D5: Level 0: Below Expectation (BE) | E5: Level 1: Developing Expectation (DE) | F5: Level 2: Meet Expectation (ME) | G5: Level 3: Above Expectation (AE)
B6: 4.1 | C6: Actively contributes to the classroom learning environment with interest, passion , and curiosity | D6: Appears uninterested and does not demonstrate or share curiosity and passion. Is defensive about feedback and suggestions. | E6: Show some interest. Rarely to ask questions and seeks information related to instruction and classroom practice. | F6: Demonstrates interest, passion, and curiosity. Asks questions and seeks information related to instruction and classroom practice. Willingly incorporates suggestions and responds appropriately to feedback. | G6: Openly contributes to the classroom learning environment as a result of their interest, passion, and curiosity.
B7: 4.2 | C7: Effeciently collects information and propose ideas to the team relevant to the group purpose | D7: Does not collect any relevant information; no useful suggestions to address team's needs. | E7: Participates in collecting general information related to the project; Do not share useful ideas to meet the team's needs. | F7: Collects basic, useful information related to the project; occasionally offers useful ideas to meet the team's needs. | G7: Collects and presents to the team a great deal of relevant information; offers welldeveloped and clearly expressed ideas directly related to the group's purpose
B8: 4.3 | C8: Participate actively all team groups and effectively conduct all assigned tasks | D8: Does not perform assigned tasks; often misses meetings and, when present, does not have anything constructive to say; relies on others to do the work. | E8: Performs some assigned tasks; miss some meetings,contributes rarely to the team work. | F8: Performs all assigned tasks; attends meetings regularly and usually participates effectively; generally reliable. | G8: Performs all tasks very effectively; attends all meetings and participates enthusiastically; very reliable.
B9: 4.4 | C9: Able as leader to to accept other team members' ideas and contribute to their development and give them full credit | D9: Often argues with team mates; doesn't let anyone else talk; occasional personal attacks and "put-downs"; wants to have things done his way and does not listen to alternate approaches. | E9: Sometimes listens to others' points of view but do not make effort to understands other ideas. | F9: Generally listens to others' points of view; always uses appropriate and respectful language; tries to make a definite effort to understand others' ideas. | G9: Always listens to others and their ideas; helps them develop their ideas while giving them full credit; always helps the team reach a fair decision.

Sheet SO6
B3: Key Performance Indicators and Rubrics for Student Outcome:
B4: 6. Support the delivery, use, and management of information systems within an information systems environment.
B5: KPI Nbr. | C5: KPI Definition | D5: Level 0: Below Expectation (BE) | E5: Level 1: Developing Expectation (DE) | F5: Level 2: Meet Expectation (ME) | G5: Level 3: Above Expectation (AE)
B6: 6.1 | C6: Recall and understand the fundamental of business concepts (i.e. marketing, accounting, human resource, etc.), its environment, and requirements | D6: Unable to understand business processes and requirements | E6: Recall some business process concepts without being able to apply them | F6: Recall and understands some business concepts and properly apply them | G6: Understands and able to properly analyse a business process in a given context and apply them
B7: 6.2 | C7: Correctly apply the the understanding of business processes and environment (i.e. marketing, finance, etc.), for developing relevant information system solutions to solve business problems | D7: Unable to apply and develop any system based on the fundamental related concept in business. | E7: Able to partially apply and develop any system based on the fundamental related concept in business. | F7: Able to show satisfactory application of business concept and develop any system based on the fundamental related concept in business. | G7: able to successfully apply business concept and develop any system based on the fundamental related concept in business.
B8: 6.3 | C8: Evaluate and relates the differences in business functions (i.e. marketing, finance, accounting, etc.) and related entities (people and processes) within the business environment, for getting user requirement and customization of IS solutions (i.e. ERP) | D8: Unable to identify and differentiate users and their roles in various different functions in the business to create requirements, and perform any customization to IS solution. | E8: Can identify and differentiate some parts of the user requirements but cannot customize the IS solution properly | F8: Can identify and differentiate most of the business user requirements and functions, and customize the IS solution satisfactorily | G8: Can successfully identify business user requirements, customize and deliver successfully the IS solution
B9: 6.4 | C9: Identify and evaluate IS technologies and business solutions (DBMS, ERP, etc) by applying knowledge of the business environment and its functional areas (management, marketing, etc.) | D9: Unable to identify and evaluate any IS solution related to any business concepts and environment | E9: Able to partially identify and evaluate IS solution related to some concepts in the business environment | F9: Able to identify and evaluate satisfactorily IS solution related to some concepts in the business environment | G9: Able to identify and evaluate successfully IS solution by effectively relating to all concepts in the business environment

Sheet SO7
B3: Key Performance Indicators and Rubrics for Student Outcome:
B4: 7. Develop and evaluate E-commerce systems on different platforms using a variety of technologies.
B5: KPI Nbr. | C5: KPI Definition | D5: Level 0: Below Expectation (BE) | E5: Level 1: Developing Expectation (DE) | F5: Level 2: Meet Expectation (ME) | G5: Level 3: Above Expectation (AE)
B6: 7.1 | C6: Properly design and develop E-commerce solutions | D6: Cannot recognize E-commerce solution development process | E6: Partially recall the phases of the development of E-commerce solutions | F6: Fully describe the process for the development of E-commerce solution without being able to apply it properly | G6: Successfully design and develop E-commerce Solution
B7: 7.2 | C7: Accurately compare and evaluate E-Commerce systems | D7: Do not recall the criteria for evaluating and comparing E-commerce solutions | E7: Recognize some of the criteria for the evaluation of E-commerce solutions | F7: Recall all the criteria for the evaluation and the comparison of E-commerce systems | G7: Successfully compare and evaluate E-commerce systems
B8: 7.3 | C8: Successfully implement E-commerce solutions on different platforms | D8: Recognize the need for using E-commerce development platforms | E8: Cite different E-commerce development platforms | F8: Partially use at least one E-commerce development plateform | G8: Conveniently use a different platforms for developing E-commerce solutions
B9: 7.4 | C9: Successfully use different technologies to develop E-commerce solutions | D9: Unable to enumerate some e-commerce development techologies | E9: Cite and partially define the usefullness of some E-commerce development technologies | F9: Partially use some E-commerce development technologies to develop relevent solutions | G9: Fully understand and use different E-commerce development technologies to deliver E-commerce solutions

Sheet SO8
B4: Rubrics for Student Outcome 8
B5: CYS-SO Apply security principles and practices to the environment , hardware, social and human aspects of a system
C6: Criterion | D6: Assessment of Criterion
D7: Above Expectation | E7: Meeting expectation | F7: Developing Expectation | G7: Below Expectation
D8: 3 | E8: 2 | F8: 1 | G8: 0
B9: 8.1 | C9: Describe security as a continuous process of tradeoffs, balancing between protection mechanisms and availability | D9: Students are able to Illustrate security as a continuous process of tradeoffs, balancing between protection mechanisms and availability. | E9: Students are able to describe security as a continuous process of tradeoffs, balancing between protection mechanisms and availability. | F9: Students are able to recognize the importance of security as a continuous process of tradeoffs. | G9: Students are not able to recognize the importance of security as a continuous process of tradeoffs.
B10: 8.2 | C10: Analyze the tradeoffs of balancing key security properties, including Confidentiality, Integrity, and Availability (CIA). | D10: Students are able to evaluate the tradeoffs of balancing key security properties, including Confidentiality, Integrity, and Availability (CIA). | E10: Students are able to analyze the tradeoffs of balancing key security properties, including Confidentiality, Integrity, and Availability (CIA) | F10: Students are able to investigate the tradeoffs of balancing key security properties, including Confidentiality, Integrity, and Availability (CIA) | G10: Students are not able to investigate the tradeoffs of balancing key security properties, including Confidentiality, Integrity, and Availability (CIA)
B11: 8.3 | C11: Illustrate through examples the concepts of security and privacy risk, threats, vulnerabilities, attack vectors, and exploits, noting there is no such thing as perfect security. | D11: Students are able to compare the concepts of risk, threats, vulnerabilities, attack vectors, and exploits to a given scenario. | E11: Students are able to illustrate through examples the concepts of risk, threats, vulnerabilities, attack vectors, and exploits, noting there is no such thing as perfect security. | F11: Students are able to differentiate the concepts of risk, threats, vulnerabilities, attack vectors, and exploits. | G11: Students are notable to differentiate the concepts of risk, threats, vulnerabilities, attack vectors, and exploits.
B13: 8.4 | C13: Apply security principles and practices for secure software development in a dynamic environment | D13: Students are able to examine security principles and practices for secure software development in a dynamic environment. | E13: Students are able to apply security principles and practices for secure software development in a dynamic environment. | F13: Students are able to summarize security principles and practices for secure software development. | G13: Students are not able to summarize security principles and practices for secure software development.

Sheet Lookup Tables
L1: SO1 | M1: Ability to identify, formulate, and solve complex engineering problems by applying principles of engineering, science, and mathematics.
L2: SO2 | M2: An ability to apply engineering design to produce solutions that meet specified needs with consideration of public health, safety, and welfare, as well as global, cultural, social, environmental, and economic factors.
L3: SO3 | M3: An ability to communicate effectively with a range of audiences.
L4: SO4 | M4: An ability to recognize ethical and professional responsibilities in engineering situations and make informed judgments, which must consider the impact of engineering solutions in global, economic, environmental, and societal contexts.
L5: SO5 | M5: An ability to function effectively on a team whose members together provide leadership, create a collaborative and inclusive environment, establish goals, plan tasks, and meet objectives.
L6: SO6 | M6: An ability to develop and conduct appropriate experimentation, analyze and interpret data, and use engineering judgment to draw conclusions
L7: SO7 | M7: An ability to acquire and apply new knowledge as needed, using appropriate learning strategies.
D8: Student's Satisfaction
C9: 0 | D9: 0 | E9: BE | F9: Below Expextations
C10: 1 | D10: 1 | E10: DE | F10: Developing Expectation
C11: 2 | D11: 2 | E11: ME | F11: Meets Expectations
C12: 3 | D12: 3 | E12: AE | F12: Accomplished Expectations | L12: Quiz
L13: Major
L14: Final
H15: 0 | I15: 0 | L15: Project
H16: 1 | I16: 1 | L16: Assignment
I17: 2
D18: Section's Satisfaction | I18: 3
D19: 59 | E19: BE | F19: Less than 60% of students are achieving the Satisfactory level (ME) or above
D20: 69 | E20: DE | F20: 60% to 69% of students are achieving the Satisfactory level (ME) or above
D21: 84 | E21: ME | F21: 70% to 79% of students are achieving the Satisfactory level (ME) or above
D22: 100 | E22: AE | F22: 90% or more of students are achieving the Satisfactory level (ME) or above
